[{"loc": "urn:cts:greekLit:tlg0085.tlg004:1", "start": 0, "length": 37}, {"loc": "urn:cts:greekLit:tlg0085.tlg004:2", "start": 37, "length": 39}, {"loc": "urn:cts:greekLit:tlg0085.tlg004:3", "start": 76, "length": 37}, {"loc": "urn:cts:greekLit:tlg0085.tlg004:4", "start": 113, "length": 37}, {"loc": "urn:cts:greekLit:tlg0085.tlg004:5", "start": 150, "length": 41}, {"loc": "urn:cts:greekLit:tlg0085.tlg004:6", "start": 191, "length": 35}, {"loc": "urn:cts:greekLit:tlg0085.tlg004:7", "start": 226, "length": 40}, {"loc": "urn:cts:greekLit:tlg0085.tlg004:8", "start": 266, "length": 35}, {"loc": "urn:cts:greekLit:tlg0085.tlg004:9", "start": 301, "length": 33}, {"loc": "urn:cts:greekLit:tlg0085.tlg004:10", "start": 334, "length": 40}, {"loc": "urn:cts:greekLit:tlg0085.tlg004:11", "start": 374, "length": 35}, {"loc": "urn:cts:greekLit:tlg0085.tlg004:12", "start": 409, "length": 36}, {"loc": "urn:cts:greekLit:tlg0085.tlg004:13", "start": 445, "length": 39}, {"loc": "urn:cts:greekLit:tlg0085.tlg004:14", "start": 484, "length": 35}, {"loc": "urn:cts:greekLit:tlg0085.tlg004:15", "start": 519, "length": 37}, {"loc": "urn:cts:greekLit:tlg0085.tlg004:16", "start": 556, "length": 40}, {"loc": "urn:cts:greekLit:tlg0085.tlg004:17", "start": 596, "length": 35}, {"loc": "urn:cts:greekLit:tlg0085.tlg004:18", "start": 631, "length": 34}, {"loc": "urn:cts:greekLit:tlg0085.tlg004:19", "start": 665, "length": 32}, {"loc": "urn:cts:greekLit:tlg0085.tlg004:20", "start": 697, "length": 39}, {"loc": "urn:cts:greekLit:tlg0085.tlg004:21", "start": 736, "length": 40}, {"loc": "urn:cts:greekLit:tlg0085.tlg004:22", "start": 776, "length": 36}, {"loc": "urn:cts:greekLit:tlg0085.tlg004:23", "start": 812, "length": 38}, {"loc": "urn:cts:greekLit:tlg0085.tlg004:24", "start": 850, "length": 40}, {"loc": "urn:cts:greekLit:tlg0085.tlg004:25", "start": 890, "length": 37}, {"loc": "urn:cts:greekLit:tlg0085.tlg004:26", "start": 927, "length": 35}, {"loc": "urn:cts:greekLit:tlg0085.tlg004:27", "start": 962, "length": 35}, {"loc": "urn:cts:greekLit:tlg0085.tlg004:28", "start": 997, "length": 33}, {"loc": "urn:cts:greekLit:tlg0085.tlg004:29", "start": 1030, "length": 37}, {"loc": "urn:cts:greekLit:tlg0085.tlg004:30", "start": 1067, "length": 41}, {"loc": "urn:cts:greekLit:tlg0085.tlg004:31", "start": 1108, "length": 38}, {"loc": "urn:cts:greekLit:tlg0085.tlg004:32", "start": 1146, "length": 33}, {"loc": "urn:cts:greekLit:tlg0085.tlg004:33", "start": 1179, "length": 38}, {"loc": "urn:cts:greekLit:tlg0085.tlg004:34", "start": 1217, "length": 37}, {"loc": "urn:cts:greekLit:tlg0085.tlg004:35", "start": 1254, "length": 37}, {"loc": "urn:cts:greekLit:tlg0085.tlg004:36", "start": 1291, "length": 39}, {"loc": "urn:cts:greekLit:tlg0085.tlg004:37", "start": 1330, "length": 35}, {"loc": "urn:cts:greekLit:tlg0085.tlg004:38", "start": 1365, "length": 39}, {"loc": "urn:cts:greekLit:tlg0085.tlg004:39", "start": 1404, "length": 34}, {"loc": "urn:cts:greekLit:tlg0085.tlg004:40", "start": 1438, "length": 36}, {"loc": "urn:cts:greekLit:tlg0085.tlg004:41", "start": 1474, "length": 42}, {"loc": "urn:cts:greekLit:tlg0085.tlg004:42", "start": 1516, "length": 36}, {"loc": "urn:cts:greekLit:tlg0085.tlg004:43", "start": 1552, "length": 36}, {"loc": "urn:cts:greekLit:tlg0085.tlg004:44", "start": 1588, "length": 38}, {"loc": "urn:cts:greekLit:tlg0085.tlg004:45", "start": 1626, "length": 35}, {"loc": "urn:cts:greekLit:tlg0085.tlg004:46", "start": 1661, "length": 31}, {"loc": "urn:cts:greekLit:tlg0085.tlg004:47", "start": 1692, "length": 35}, {"loc": "urn:cts:greekLit:tlg0085.tlg004:48", "start": 1727, "length": 36}, {"loc": "urn:cts:greekLit:tlg0085.tlg004:49", "start": 1763, "length": 41}, {"loc": "urn:cts:greekLit:tlg0085.tlg004:50", "start": 1804, "length": 41}, {"loc": "urn:cts:greekLit:tlg0085.tlg004:51", "start": 1845, "length": 41}, {"loc": "urn:cts:greekLit:tlg0085.tlg004:52", "start": 1886, "length": 36}, {"loc": "urn:cts:greekLit:tlg0085.tlg004:53", "start": 1922, "length": 34}, {"loc": "urn:cts:greekLit:tlg0085.tlg004:54", "start": 1956, "length": 38}, {"loc": "urn:cts:greekLit:tlg0085.tlg004:55", "start": 1994, "length": 39}, {"loc": "urn:cts:greekLit:tlg0085.tlg004:56", "start": 2033, "length": 37}, {"loc": "urn:cts:greekLit:tlg0085.tlg004:57", "start": 2070, "length": 44}, {"loc": "urn:cts:greekLit:tlg0085.tlg004:58", "start": 2114, "length": 35}, {"loc": "urn:cts:greekLit:tlg0085.tlg004:59", "start": 2149, "length": 39}, {"loc": "urn:cts:greekLit:tlg0085.tlg004:60", "start": 2188, "length": 39}, {"loc": "urn:cts:greekLit:tlg0085.tlg004:61", "start": 2227, "length": 41}, {"loc": "urn:cts:greekLit:tlg0085.tlg004:62", "start": 2268, "length": 36}, {"loc": "urn:cts:greekLit:tlg0085.tlg004:63", "start": 2304, "length": 38}, {"loc": "urn:cts:greekLit:tlg0085.tlg004:64", "start": 2342, "length": 38}, {"loc": "urn:cts:greekLit:tlg0085.tlg004:65", "start": 2380, "length": 37}, {"loc": "urn:cts:greekLit:tlg0085.tlg004:66", "start": 2417, "length": 33}, {"loc": "urn:cts:greekLit:tlg0085.tlg004:67", "start": 2450, "length": 33}, {"loc": "urn:cts:greekLit:tlg0085.tlg004:68", "start": 2483, "length": 34}, {"loc": "urn:cts:greekLit:tlg0085.tlg004:69", "start": 2517, "length": 38}, {"loc": "urn:cts:greekLit:tlg0085.tlg004:70", "start": 2555, "length": 35}, {"loc": "urn:cts:greekLit:tlg0085.tlg004:71", "start": 2590, "length": 37}, {"loc": "urn:cts:greekLit:tlg0085.tlg004:72", "start": 2627, "length": 30}, {"loc": "urn:cts:greekLit:tlg0085.tlg004:73", "start": 2657, "length": 39}, {"loc": "urn:cts:greekLit:tlg0085.tlg004:74", "start": 2696, "length": 37}, {"loc": "urn:cts:greekLit:tlg0085.tlg004:75", "start": 2733, "length": 34}, {"loc": "urn:cts:greekLit:tlg0085.tlg004:76", "start": 2767, "length": 40}, {"loc": "urn:cts:greekLit:tlg0085.tlg004:77", "start": 2807, "length": 38}, {"loc": "urn:cts:greekLit:tlg0085.tlg004:78", "start": 2845, "length": 27}, {"loc": "urn:cts:greekLit:tlg0085.tlg004:79", "start": 2872, "length": 36}, {"loc": "urn:cts:greekLit:tlg0085.tlg004:80", "start": 2908, "length": 38}, {"loc": "urn:cts:greekLit:tlg0085.tlg004:81", "start": 2946, "length": 33}, {"loc": "urn:cts:greekLit:tlg0085.tlg004:82", "start": 2979, "length": 30}, {"loc": "urn:cts:greekLit:tlg0085.tlg004:83", "start": 3009, "length": 35}, {"loc": "urn:cts:greekLit:tlg0085.tlg004:84", "start": 3044, "length": 37}, {"loc": "urn:cts:greekLit:tlg0085.tlg004:85", "start": 3081, "length": 32}, {"loc": "urn:cts:greekLit:tlg0085.tlg004:86", "start": 3113, "length": 6}, {"loc": "urn:cts:greekLit:tlg0085.tlg004:87", "start": 3119, "length": 31}, {"loc": "urn:cts:greekLit:tlg0085.tlg004:88", "start": 3150, "length": 27}, {"loc": "urn:cts:greekLit:tlg0085.tlg004:89", "start": 3177, "length": 29}, {"loc": "urn:cts:greekLit:tlg0085.tlg004:90", "start": 3206, "length": 30}, {"loc": "urn:cts:greekLit:tlg0085.tlg004:91", "start": 3236, "length": 35}, {"loc": "urn:cts:greekLit:tlg0085.tlg004:92", "start": 3271, "length": 13}, {"loc": "urn:cts:greekLit:tlg0085.tlg004:93", "start": 3284, "length": 32}, {"loc": "urn:cts:greekLit:tlg0085.tlg004:95", "start": 3316, "length": 16}, {"loc": "urn:cts:greekLit:tlg0085.tlg004:96", "start": 3332, "length": 20}, {"loc": "urn:cts:greekLit:tlg0085.tlg004:97", "start": 3352, "length": 33}, {"loc": "urn:cts:greekLit:tlg0085.tlg004:98", "start": 3385, "length": 17}, {"loc": "urn:cts:greekLit:tlg0085.tlg004:100", "start": 3402, "length": 38}, {"loc": "urn:cts:greekLit:tlg0085.tlg004:101", "start": 3440, "length": 38}, {"loc": "urn:cts:greekLit:tlg0085.tlg004:102", "start": 3478, "length": 18}, {"loc": "urn:cts:greekLit:tlg0085.tlg004:103", "start": 3496, "length": 40}, {"loc": "urn:cts:greekLit:tlg0085.tlg004:104", "start": 3536, "length": 32}, {"loc": "urn:cts:greekLit:tlg0085.tlg004:105", "start": 3568, "length": 16}, {"loc": "urn:cts:greekLit:tlg0085.tlg004:106", "start": 3584, "length": 32}, {"loc": "urn:cts:greekLit:tlg0085.tlg004:107", "start": 3616, "length": 33}, {"loc": "urn:cts:greekLit:tlg0085.tlg004:109", "start": 3649, "length": 34}, {"loc": "urn:cts:greekLit:tlg0085.tlg004:110", "start": 3683, "length": 15}, {"loc": "urn:cts:greekLit:tlg0085.tlg004:111", "start": 3698, "length": 31}, {"loc": "urn:cts:greekLit:tlg0085.tlg004:112", "start": 3729, "length": 39}, {"loc": "urn:cts:greekLit:tlg0085.tlg004:115", "start": 3768, "length": 32}, {"loc": "urn:cts:greekLit:tlg0085.tlg004:116", "start": 3800, "length": 28}, {"loc": "urn:cts:greekLit:tlg0085.tlg004:117", "start": 3828, "length": 28}, {"loc": "urn:cts:greekLit:tlg0085.tlg004:120", "start": 3856, "length": 26}, {"loc": "urn:cts:greekLit:tlg0085.tlg004:121", "start": 3882, "length": 33}, {"loc": "urn:cts:greekLit:tlg0085.tlg004:122", "start": 3915, "length": 32}, {"loc": "urn:cts:greekLit:tlg0085.tlg004:123", "start": 3947, "length": 26}, {"loc": "urn:cts:greekLit:tlg0085.tlg004:124", "start": 3973, "length": 35}, {"loc": "urn:cts:greekLit:tlg0085.tlg004:125", "start": 4008, "length": 33}, {"loc": "urn:cts:greekLit:tlg0085.tlg004:126", "start": 4041, "length": 1}, {"loc": "urn:cts:greekLit:tlg0085.tlg004:127", "start": 4042, "length": 28}, {"loc": "urn:cts:greekLit:tlg0085.tlg004:128", "start": 4070, "length": 36}, {"loc": "urn:cts:greekLit:tlg0085.tlg004:129", "start": 4106, "length": 17}, {"loc": "urn:cts:greekLit:tlg0085.tlg004:130", "start": 4123, "length": 36}, {"loc": "urn:cts:greekLit:tlg0085.tlg004:131", "start": 4159, "length": 27}, {"loc": "urn:cts:greekLit:tlg0085.tlg004:132", "start": 4186, "length": 32}, {"loc": "urn:cts:greekLit:tlg0085.tlg004:135", "start": 4218, "length": 38}, {"loc": "urn:cts:greekLit:tlg0085.tlg004:136", "start": 4256, "length": 35}, {"loc": "urn:cts:greekLit:tlg0085.tlg004:140", "start": 4291, "length": 36}, {"loc": "urn:cts:greekLit:tlg0085.tlg004:141", "start": 4327, "length": 30}, {"loc": "urn:cts:greekLit:tlg0085.tlg004:142", "start": 4357, "length": 33}, {"loc": "urn:cts:greekLit:tlg0085.tlg004:143", "start": 4390, "length": 22}, {"loc": "urn:cts:greekLit:tlg0085.tlg004:145", "start": 4412, "length": 35}, {"loc": "urn:cts:greekLit:tlg0085.tlg004:146", "start": 4447, "length": 28}, {"loc": "urn:cts:greekLit:tlg0085.tlg004:147", "start": 4475, "length": 20}, {"loc": "urn:cts:greekLit:tlg0085.tlg004:148", "start": 4495, "length": 38}, {"loc": "urn:cts:greekLit:tlg0085.tlg004:149", "start": 4533, "length": 9}, {"loc": "urn:cts:greekLit:tlg0085.tlg004:150", "start": 4542, "length": 32}, {"loc": "urn:cts:greekLit:tlg0085.tlg004:151", "start": 4574, "length": 14}, {"loc": "urn:cts:greekLit:tlg0085.tlg004:152", "start": 4588, "length": 32}, {"loc": "urn:cts:greekLit:tlg0085.tlg004:153", "start": 4620, "length": 22}, {"loc": "urn:cts:greekLit:tlg0085.tlg004:155", "start": 4642, "length": 35}, {"loc": "urn:cts:greekLit:tlg0085.tlg004:156", "start": 4677, "length": 36}, {"loc": "urn:cts:greekLit:tlg0085.tlg004:157", "start": 4713, "length": 30}, {"loc": "urn:cts:greekLit:tlg0085.tlg004:158", "start": 4743, "length": 9}, {"loc": "urn:cts:greekLit:tlg0085.tlg004:158b", "start": 4752, "length": 37}, {"loc": "urn:cts:greekLit:tlg0085.tlg004:159", "start": 4789, "length": 16}, {"loc": "urn:cts:greekLit:tlg0085.tlg004:160", "start": 4805, "length": 37}, {"loc": "urn:cts:greekLit:tlg0085.tlg004:161", "start": 4842, "length": 15}, {"loc": "urn:cts:greekLit:tlg0085.tlg004:162", "start": 4857, "length": 35}, {"loc": "urn:cts:greekLit:tlg0085.tlg004:163", "start": 4892, "length": 39}, {"loc": "urn:cts:greekLit:tlg0085.tlg004:165", "start": 4931, "length": 25}, {"loc": "urn:cts:greekLit:tlg0085.tlg004:166", "start": 4956, "length": 19}, {"loc": "urn:cts:greekLit:tlg0085.tlg004:167", "start": 4975, "length": 26}, {"loc": "urn:cts:greekLit:tlg0085.tlg004:168", "start": 5001, "length": 20}, {"loc": "urn:cts:greekLit:tlg0085.tlg004:169", "start": 5021, "length": 27}, {"loc": "urn:cts:greekLit:tlg0085.tlg004:170", "start": 5048, "length": 18}, {"loc": "urn:cts:greekLit:tlg0085.tlg004:171", "start": 5066, "length": 32}, {"loc": "urn:cts:greekLit:tlg0085.tlg004:172", "start": 5098, "length": 19}, {"loc": "urn:cts:greekLit:tlg0085.tlg004:174", "start": 5117, "length": 19}, {"loc": "urn:cts:greekLit:tlg0085.tlg004:175", "start": 5136, "length": 30}, {"loc": "urn:cts:greekLit:tlg0085.tlg004:176", "start": 5166, "length": 23}, {"loc": "urn:cts:greekLit:tlg0085.tlg004:177", "start": 5189, "length": 25}, {"loc": "urn:cts:greekLit:tlg0085.tlg004:178", "start": 5214, "length": 22}, {"loc": "urn:cts:greekLit:tlg0085.tlg004:179", "start": 5236, "length": 31}, {"loc": "urn:cts:greekLit:tlg0085.tlg004:180", "start": 5267, "length": 20}, {"loc": "urn:cts:greekLit:tlg0085.tlg004:181", "start": 5287, "length": 35}, {"loc": "urn:cts:greekLit:tlg0085.tlg004:182", "start": 5322, "length": 34}, {"loc": "urn:cts:greekLit:tlg0085.tlg004:183", "start": 5356, "length": 36}, {"loc": "urn:cts:greekLit:tlg0085.tlg004:185", "start": 5392, "length": 37}, {"loc": "urn:cts:greekLit:tlg0085.tlg004:186", "start": 5429, "length": 36}, {"loc": "urn:cts:greekLit:tlg0085.tlg004:187", "start": 5465, "length": 37}, {"loc": "urn:cts:greekLit:tlg0085.tlg004:188", "start": 5502, "length": 34}, {"loc": "urn:cts:greekLit:tlg0085.tlg004:189", "start": 5536, "length": 38}, {"loc": "urn:cts:greekLit:tlg0085.tlg004:190", "start": 5574, "length": 39}, {"loc": "urn:cts:greekLit:tlg0085.tlg004:191", "start": 5613, "length": 40}, {"loc": "urn:cts:greekLit:tlg0085.tlg004:192", "start": 5653, "length": 34}, {"loc": "urn:cts:greekLit:tlg0085.tlg004:193", "start": 5687, "length": 39}, {"loc": "urn:cts:greekLit:tlg0085.tlg004:194", "start": 5726, "length": 39}, {"loc": "urn:cts:greekLit:tlg0085.tlg004:195", "start": 5765, "length": 36}, {"loc": "urn:cts:greekLit:tlg0085.tlg004:196", "start": 5801, "length": 37}, {"loc": "urn:cts:greekLit:tlg0085.tlg004:197", "start": 5838, "length": 35}, {"loc": "urn:cts:greekLit:tlg0085.tlg004:198", "start": 5873, "length": 38}, {"loc": "urn:cts:greekLit:tlg0085.tlg004:199", "start": 5911, "length": 39}, {"loc": "urn:cts:greekLit:tlg0085.tlg004:200", "start": 5950, "length": 36}, {"loc": "urn:cts:greekLit:tlg0085.tlg004:201", "start": 5986, "length": 40}, {"loc": "urn:cts:greekLit:tlg0085.tlg004:202", "start": 6026, "length": 36}, {"loc": "urn:cts:greekLit:tlg0085.tlg004:203", "start": 6062, "length": 36}, {"loc": "urn:cts:greekLit:tlg0085.tlg004:204", "start": 6098, "length": 37}, {"loc": "urn:cts:greekLit:tlg0085.tlg004:205", "start": 6135, "length": 36}, {"loc": "urn:cts:greekLit:tlg0085.tlg004:206", "start": 6171, "length": 36}, {"loc": "urn:cts:greekLit:tlg0085.tlg004:207", "start": 6207, "length": 21}, {"loc": "urn:cts:greekLit:tlg0085.tlg004:208", "start": 6228, "length": 40}, {"loc": "urn:cts:greekLit:tlg0085.tlg004:209", "start": 6268, "length": 33}, {"loc": "urn:cts:greekLit:tlg0085.tlg004:210", "start": 6301, "length": 35}, {"loc": "urn:cts:greekLit:tlg0085.tlg004:211", "start": 6336, "length": 38}, {"loc": "urn:cts:greekLit:tlg0085.tlg004:212", "start": 6374, "length": 36}, {"loc": "urn:cts:greekLit:tlg0085.tlg004:213", "start": 6410, "length": 39}, {"loc": "urn:cts:greekLit:tlg0085.tlg004:214", "start": 6449, "length": 46}, {"loc": "urn:cts:greekLit:tlg0085.tlg004:215", "start": 6495, "length": 22}, {"loc": "urn:cts:greekLit:tlg0085.tlg004:216", "start": 6517, "length": 38}, {"loc": "urn:cts:greekLit:tlg0085.tlg004:217", "start": 6555, "length": 44}, {"loc": "urn:cts:greekLit:tlg0085.tlg004:218", "start": 6599, "length": 41}, {"loc": "urn:cts:greekLit:tlg0085.tlg004:219", "start": 6640, "length": 34}, {"loc": "urn:cts:greekLit:tlg0085.tlg004:220", "start": 6674, "length": 35}, {"loc": "urn:cts:greekLit:tlg0085.tlg004:221", "start": 6709, "length": 36}, {"loc": "urn:cts:greekLit:tlg0085.tlg004:222", "start": 6745, "length": 21}, {"loc": "urn:cts:greekLit:tlg0085.tlg004:223", "start": 6766, "length": 37}, {"loc": "urn:cts:greekLit:tlg0085.tlg004:224", "start": 6803, "length": 33}, {"loc": "urn:cts:greekLit:tlg0085.tlg004:225", "start": 6836, "length": 37}, {"loc": "urn:cts:greekLit:tlg0085.tlg004:226", "start": 6873, "length": 37}, {"loc": "urn:cts:greekLit:tlg0085.tlg004:227", "start": 6910, "length": 35}, {"loc": "urn:cts:greekLit:tlg0085.tlg004:228", "start": 6945, "length": 32}, {"loc": "urn:cts:greekLit:tlg0085.tlg004:229", "start": 6977, "length": 27}, {"loc": "urn:cts:greekLit:tlg0085.tlg004:230", "start": 7004, "length": 39}, {"loc": "urn:cts:greekLit:tlg0085.tlg004:231", "start": 7043, "length": 38}, {"loc": "urn:cts:greekLit:tlg0085.tlg004:232", "start": 7081, "length": 42}, {"loc": "urn:cts:greekLit:tlg0085.tlg004:233", "start": 7123, "length": 34}, {"loc": "urn:cts:greekLit:tlg0085.tlg004:234", "start": 7157, "length": 37}, {"loc": "urn:cts:greekLit:tlg0085.tlg004:235", "start": 7194, "length": 25}, {"loc": "urn:cts:greekLit:tlg0085.tlg004:236", "start": 7219, "length": 38}, {"loc": "urn:cts:greekLit:tlg0085.tlg004:237", "start": 7257, "length": 41}, {"loc": "urn:cts:greekLit:tlg0085.tlg004:238", "start": 7298, "length": 34}, {"loc": "urn:cts:greekLit:tlg0085.tlg004:239", "start": 7332, "length": 34}, {"loc": "urn:cts:greekLit:tlg0085.tlg004:240", "start": 7366, "length": 36}, {"loc": "urn:cts:greekLit:tlg0085.tlg004:241", "start": 7402, "length": 21}, {"loc": "urn:cts:greekLit:tlg0085.tlg004:242", "start": 7423, "length": 37}, {"loc": "urn:cts:greekLit:tlg0085.tlg004:243", "start": 7460, "length": 32}, {"loc": "urn:cts:greekLit:tlg0085.tlg004:244", "start": 7492, "length": 38}, {"loc": "urn:cts:greekLit:tlg0085.tlg004:245", "start": 7530, "length": 37}, {"loc": "urn:cts:greekLit:tlg0085.tlg004:246", "start": 7567, "length": 36}, {"loc": "urn:cts:greekLit:tlg0085.tlg004:247", "start": 7603, "length": 38}, {"loc": "urn:cts:greekLit:tlg0085.tlg004:248", "start": 7641, "length": 39}, {"loc": "urn:cts:greekLit:tlg0085.tlg004:249", "start": 7680, "length": 41}, {"loc": "urn:cts:greekLit:tlg0085.tlg004:250", "start": 7721, "length": 39}, {"loc": "urn:cts:greekLit:tlg0085.tlg004:251", "start": 7760, "length": 34}, {"loc": "urn:cts:greekLit:tlg0085.tlg004:252", "start": 7794, "length": 36}, {"loc": "urn:cts:greekLit:tlg0085.tlg004:253", "start": 7830, "length": 37}, {"loc": "urn:cts:greekLit:tlg0085.tlg004:254", "start": 7867, "length": 38}, {"loc": "urn:cts:greekLit:tlg0085.tlg004:255", "start": 7905, "length": 43}, {"loc": "urn:cts:greekLit:tlg0085.tlg004:256", "start": 7948, "length": 35}, {"loc": "urn:cts:greekLit:tlg0085.tlg004:257", "start": 7983, "length": 37}, {"loc": "urn:cts:greekLit:tlg0085.tlg004:258", "start": 8020, "length": 38}, {"loc": "urn:cts:greekLit:tlg0085.tlg004:259", "start": 8058, "length": 34}, {"loc": "urn:cts:greekLit:tlg0085.tlg004:260", "start": 8092, "length": 37}, {"loc": "urn:cts:greekLit:tlg0085.tlg004:261", "start": 8129, "length": 40}, {"loc": "urn:cts:greekLit:tlg0085.tlg004:262", "start": 8169, "length": 37}, {"loc": "urn:cts:greekLit:tlg0085.tlg004:263", "start": 8206, "length": 39}, {"loc": "urn:cts:greekLit:tlg0085.tlg004:264", "start": 8245, "length": 42}, {"loc": "urn:cts:greekLit:tlg0085.tlg004:265", "start": 8287, "length": 43}, {"loc": "urn:cts:greekLit:tlg0085.tlg004:266", "start": 8330, "length": 41}, {"loc": "urn:cts:greekLit:tlg0085.tlg004:267", "start": 8371, "length": 35}, {"loc": "urn:cts:greekLit:tlg0085.tlg004:268", "start": 8406, "length": 34}, {"loc": "urn:cts:greekLit:tlg0085.tlg004:269", "start": 8440, "length": 33}, {"loc": "urn:cts:greekLit:tlg0085.tlg004:270", "start": 8473, "length": 38}, {"loc": "urn:cts:greekLit:tlg0085.tlg004:271", "start": 8511, "length": 38}, {"loc": "urn:cts:greekLit:tlg0085.tlg004:272", "start": 8549, "length": 35}, {"loc": "urn:cts:greekLit:tlg0085.tlg004:273", "start": 8584, "length": 40}, {"loc": "urn:cts:greekLit:tlg0085.tlg004:274", "start": 8624, "length": 37}, {"loc": "urn:cts:greekLit:tlg0085.tlg004:275", "start": 8661, "length": 34}, {"loc": "urn:cts:greekLit:tlg0085.tlg004:276", "start": 8695, "length": 39}, {"loc": "urn:cts:greekLit:tlg0085.tlg004:277", "start": 8734, "length": 35}, {"loc": "urn:cts:greekLit:tlg0085.tlg004:278", "start": 8769, "length": 40}, {"loc": "urn:cts:greekLit:tlg0085.tlg004:279", "start": 8809, "length": 38}, {"loc": "urn:cts:greekLit:tlg0085.tlg004:280", "start": 8847, "length": 37}, {"loc": "urn:cts:greekLit:tlg0085.tlg004:281", "start": 8884, "length": 39}, {"loc": "urn:cts:greekLit:tlg0085.tlg004:282", "start": 8923, "length": 39}, {"loc": "urn:cts:greekLit:tlg0085.tlg004:283", "start": 8962, "length": 36}, {"loc": "urn:cts:greekLit:tlg0085.tlg004:284", "start": 8998, "length": 36}, {"loc": "urn:cts:greekLit:tlg0085.tlg004:285", "start": 9034, "length": 36}, {"loc": "urn:cts:greekLit:tlg0085.tlg004:286", "start": 9070, "length": 43}, {"loc": "urn:cts:greekLit:tlg0085.tlg004:287", "start": 9113, "length": 39}, {"loc": "urn:cts:greekLit:tlg0085.tlg004:288", "start": 9152, "length": 34}, {"loc": "urn:cts:greekLit:tlg0085.tlg004:289", "start": 9186, "length": 20}, {"loc": "urn:cts:greekLit:tlg0085.tlg004:290", "start": 9206, "length": 26}, {"loc": "urn:cts:greekLit:tlg0085.tlg004:291", "start": 9232, "length": 20}, {"loc": "urn:cts:greekLit:tlg0085.tlg004:292", "start": 9252, "length": 24}, {"loc": "urn:cts:greekLit:tlg0085.tlg004:293", "start": 9276, "length": 34}, {"loc": "urn:cts:greekLit:tlg0085.tlg004:294", "start": 9310, "length": 19}, {"loc": "urn:cts:greekLit:tlg0085.tlg004:295", "start": 9329, "length": 25}, {"loc": "urn:cts:greekLit:tlg0085.tlg004:296", "start": 9354, "length": 19}, {"loc": "urn:cts:greekLit:tlg0085.tlg004:297", "start": 9373, "length": 24}, {"loc": "urn:cts:greekLit:tlg0085.tlg004:298", "start": 9397, "length": 24}, {"loc": "urn:cts:greekLit:tlg0085.tlg004:299", "start": 9421, "length": 18}, {"loc": "urn:cts:greekLit:tlg0085.tlg004:300", "start": 9439, "length": 20}, {"loc": "urn:cts:greekLit:tlg0085.tlg004:301", "start": 9459, "length": 23}, {"loc": "urn:cts:greekLit:tlg0085.tlg004:302", "start": 9482, "length": 24}, {"loc": "urn:cts:greekLit:tlg0085.tlg004:303", "start": 9506, "length": 18}, {"loc": "urn:cts:greekLit:tlg0085.tlg004:304", "start": 9524, "length": 31}, {"loc": "urn:cts:greekLit:tlg0085.tlg004:305", "start": 9555, "length": 22}, {"loc": "urn:cts:greekLit:tlg0085.tlg004:306", "start": 9577, "length": 28}, {"loc": "urn:cts:greekLit:tlg0085.tlg004:307", "start": 9605, "length": 22}, {"loc": "urn:cts:greekLit:tlg0085.tlg004:308", "start": 9627, "length": 20}, {"loc": "urn:cts:greekLit:tlg0085.tlg004:309", "start": 9647, "length": 18}, {"loc": "urn:cts:greekLit:tlg0085.tlg004:310", "start": 9665, "length": 15}, {"loc": "urn:cts:greekLit:tlg0085.tlg004:311", "start": 9680, "length": 18}, {"loc": "urn:cts:greekLit:tlg0085.tlg004:312", "start": 9698, "length": 23}, {"loc": "urn:cts:greekLit:tlg0085.tlg004:313", "start": 9721, "length": 20}, {"loc": "urn:cts:greekLit:tlg0085.tlg004:314", "start": 9741, "length": 21}, {"loc": "urn:cts:greekLit:tlg0085.tlg004:315", "start": 9762, "length": 21}, {"loc": "urn:cts:greekLit:tlg0085.tlg004:316", "start": 9783, "length": 19}, {"loc": "urn:cts:greekLit:tlg0085.tlg004:317", "start": 9802, "length": 23}, {"loc": "urn:cts:greekLit:tlg0085.tlg004:318", "start": 9825, "length": 24}, {"loc": "urn:cts:greekLit:tlg0085.tlg004:319", "start": 9849, "length": 19}, {"loc": "urn:cts:greekLit:tlg0085.tlg004:320", "start": 9868, "length": 19}, {"loc": "urn:cts:greekLit:tlg0085.tlg004:321", "start": 9887, "length": 30}, {"loc": "urn:cts:greekLit:tlg0085.tlg004:322", "start": 9917, "length": 27}, {"loc": "urn:cts:greekLit:tlg0085.tlg004:323", "start": 9944, "length": 21}, {"loc": "urn:cts:greekLit:tlg0085.tlg004:324", "start": 9965, "length": 25}, {"loc": "urn:cts:greekLit:tlg0085.tlg004:325", "start": 9990, "length": 19}, {"loc": "urn:cts:greekLit:tlg0085.tlg004:326", "start": 10009, "length": 29}, {"loc": "urn:cts:greekLit:tlg0085.tlg004:327", "start": 10038, "length": 25}, {"loc": "urn:cts:greekLit:tlg0085.tlg004:328", "start": 10063, "length": 25}, {"loc": "urn:cts:greekLit:tlg0085.tlg004:329", "start": 10088, "length": 23}, {"loc": "urn:cts:greekLit:tlg0085.tlg004:330", "start": 10111, "length": 22}, {"loc": "urn:cts:greekLit:tlg0085.tlg004:331", "start": 10133, "length": 28}, {"loc": "urn:cts:greekLit:tlg0085.tlg004:332", "start": 10161, "length": 28}, {"loc": "urn:cts:greekLit:tlg0085.tlg004:333", "start": 10189, "length": 34}, {"loc": "urn:cts:greekLit:tlg0085.tlg004:334", "start": 10223, "length": 30}, {"loc": "urn:cts:greekLit:tlg0085.tlg004:335", "start": 10253, "length": 23}, {"loc": "urn:cts:greekLit:tlg0085.tlg004:336", "start": 10276, "length": 29}, {"loc": "urn:cts:greekLit:tlg0085.tlg004:337", "start": 10305, "length": 24}, {"loc": "urn:cts:greekLit:tlg0085.tlg004:338", "start": 10329, "length": 32}, {"loc": "urn:cts:greekLit:tlg0085.tlg004:339", "start": 10361, "length": 25}, {"loc": "urn:cts:greekLit:tlg0085.tlg004:340", "start": 10386, "length": 28}, {"loc": "urn:cts:greekLit:tlg0085.tlg004:341", "start": 10414, "length": 26}, {"loc": "urn:cts:greekLit:tlg0085.tlg004:342", "start": 10440, "length": 27}, {"loc": "urn:cts:greekLit:tlg0085.tlg004:343", "start": 10467, "length": 31}, {"loc": "urn:cts:greekLit:tlg0085.tlg004:344", "start": 10498, "length": 24}, {"loc": "urn:cts:greekLit:tlg0085.tlg004:345", "start": 10522, "length": 37}, {"loc": "urn:cts:greekLit:tlg0085.tlg004:345b", "start": 10559, "length": 10}, {"loc": "urn:cts:greekLit:tlg0085.tlg004:346", "start": 10569, "length": 30}, {"loc": "urn:cts:greekLit:tlg0085.tlg004:347", "start": 10599, "length": 20}, {"loc": "urn:cts:greekLit:tlg0085.tlg004:348", "start": 10619, "length": 22}, {"loc": "urn:cts:greekLit:tlg0085.tlg004:349", "start": 10641, "length": 17}, {"loc": "urn:cts:greekLit:tlg0085.tlg004:350", "start": 10658, "length": 23}, {"loc": "urn:cts:greekLit:tlg0085.tlg004:351", "start": 10681, "length": 32}, {"loc": "urn:cts:greekLit:tlg0085.tlg004:352", "start": 10713, "length": 24}, {"loc": "urn:cts:greekLit:tlg0085.tlg004:353", "start": 10737, "length": 23}, {"loc": "urn:cts:greekLit:tlg0085.tlg004:354", "start": 10760, "length": 22}, {"loc": "urn:cts:greekLit:tlg0085.tlg004:355", "start": 10782, "length": 33}, {"loc": "urn:cts:greekLit:tlg0085.tlg004:356", "start": 10815, "length": 30}, {"loc": "urn:cts:greekLit:tlg0085.tlg004:357", "start": 10845, "length": 35}, {"loc": "urn:cts:greekLit:tlg0085.tlg004:358", "start": 10880, "length": 27}, {"loc": "urn:cts:greekLit:tlg0085.tlg004:359", "start": 10907, "length": 18}, {"loc": "urn:cts:greekLit:tlg0085.tlg004:360", "start": 10925, "length": 22}, {"loc": "urn:cts:greekLit:tlg0085.tlg004:361", "start": 10947, "length": 21}, {"loc": "urn:cts:greekLit:tlg0085.tlg004:362", "start": 10968, "length": 21}, {"loc": "urn:cts:greekLit:tlg0085.tlg004:363", "start": 10989, "length": 30}, {"loc": "urn:cts:greekLit:tlg0085.tlg004:364", "start": 11019, "length": 25}, {"loc": "urn:cts:greekLit:tlg0085.tlg004:365", "start": 11044, "length": 22}, {"loc": "urn:cts:greekLit:tlg0085.tlg004:366", "start": 11066, "length": 20}, {"loc": "urn:cts:greekLit:tlg0085.tlg004:367", "start": 11086, "length": 34}, {"loc": "urn:cts:greekLit:tlg0085.tlg004:368", "start": 11120, "length": 29}, {"loc": "urn:cts:greekLit:tlg0085.tlg004:369", "start": 11149, "length": 39}, {"loc": "urn:cts:greekLit:tlg0085.tlg004:370", "start": 11188, "length": 38}, {"loc": "urn:cts:greekLit:tlg0085.tlg004:371", "start": 11226, "length": 37}, {"loc": "urn:cts:greekLit:tlg0085.tlg004:372", "start": 11263, "length": 37}, {"loc": "urn:cts:greekLit:tlg0085.tlg004:373", "start": 11300, "length": 37}, {"loc": "urn:cts:greekLit:tlg0085.tlg004:374", "start": 11337, "length": 40}, {"loc": "urn:cts:greekLit:tlg0085.tlg004:375", "start": 11377, "length": 37}, {"loc": "urn:cts:greekLit:tlg0085.tlg004:376", "start": 11414, "length": 39}, {"loc": "urn:cts:greekLit:tlg0085.tlg004:377", "start": 11453, "length": 38}, {"loc": "urn:cts:greekLit:tlg0085.tlg004:378", "start": 11491, "length": 38}, {"loc": "urn:cts:greekLit:tlg0085.tlg004:379", "start": 11529, "length": 39}, {"loc": "urn:cts:greekLit:tlg0085.tlg004:380", "start": 11568, "length": 38}, {"loc": "urn:cts:greekLit:tlg0085.tlg004:381", "start": 11606, "length": 39}, {"loc": "urn:cts:greekLit:tlg0085.tlg004:382", "start": 11645, "length": 42}, {"loc": "urn:cts:greekLit:tlg0085.tlg004:383", "start": 11687, "length": 35}, {"loc": "urn:cts:greekLit:tlg0085.tlg004:384", "start": 11722, "length": 38}, {"loc": "urn:cts:greekLit:tlg0085.tlg004:385", "start": 11760, "length": 43}, {"loc": "urn:cts:greekLit:tlg0085.tlg004:386", "start": 11803, "length": 35}, {"loc": "urn:cts:greekLit:tlg0085.tlg004:387", "start": 11838, "length": 40}, {"loc": "urn:cts:greekLit:tlg0085.tlg004:388", "start": 11878, "length": 41}, {"loc": "urn:cts:greekLit:tlg0085.tlg004:389", "start": 11919, "length": 36}, {"loc": "urn:cts:greekLit:tlg0085.tlg004:390", "start": 11955, "length": 44}, {"loc": "urn:cts:greekLit:tlg0085.tlg004:391", "start": 11999, "length": 38}, {"loc": "urn:cts:greekLit:tlg0085.tlg004:392", "start": 12037, "length": 39}, {"loc": "urn:cts:greekLit:tlg0085.tlg004:393", "start": 12076, "length": 37}, {"loc": "urn:cts:greekLit:tlg0085.tlg004:394", "start": 12113, "length": 37}, {"loc": "urn:cts:greekLit:tlg0085.tlg004:395", "start": 12150, "length": 40}, {"loc": "urn:cts:greekLit:tlg0085.tlg004:396", "start": 12190, "length": 39}, {"loc": "urn:cts:greekLit:tlg0085.tlg004:397", "start": 12229, "length": 42}, {"loc": "urn:cts:greekLit:tlg0085.tlg004:398", "start": 12271, "length": 34}, {"loc": "urn:cts:greekLit:tlg0085.tlg004:399", "start": 12305, "length": 42}, {"loc": "urn:cts:greekLit:tlg0085.tlg004:400", "start": 12347, "length": 39}, {"loc": "urn:cts:greekLit:tlg0085.tlg004:401", "start": 12386, "length": 38}, {"loc": "urn:cts:greekLit:tlg0085.tlg004:402", "start": 12424, "length": 37}, {"loc": "urn:cts:greekLit:tlg0085.tlg004:403", "start": 12461, "length": 40}, {"loc": "urn:cts:greekLit:tlg0085.tlg004:404", "start": 12501, "length": 36}, {"loc": "urn:cts:greekLit:tlg0085.tlg004:405", "start": 12537, "length": 38}, {"loc": "urn:cts:greekLit:tlg0085.tlg004:406", "start": 12575, "length": 43}, {"loc": "urn:cts:greekLit:tlg0085.tlg004:407", "start": 12618, "length": 34}, {"loc": "urn:cts:greekLit:tlg0085.tlg004:408", "start": 12652, "length": 36}, {"loc": "urn:cts:greekLit:tlg0085.tlg004:409", "start": 12688, "length": 39}, {"loc": "urn:cts:greekLit:tlg0085.tlg004:410", "start": 12727, "length": 41}, {"loc": "urn:cts:greekLit:tlg0085.tlg004:411", "start": 12768, "length": 44}, {"loc": "urn:cts:greekLit:tlg0085.tlg004:412", "start": 12812, "length": 41}, {"loc": "urn:cts:greekLit:tlg0085.tlg004:413", "start": 12853, "length": 40}, {"loc": "urn:cts:greekLit:tlg0085.tlg004:414", "start": 12893, "length": 44}, {"loc": "urn:cts:greekLit:tlg0085.tlg004:415", "start": 12937, "length": 39}, {"loc": "urn:cts:greekLit:tlg0085.tlg004:416", "start": 12976, "length": 37}, {"loc": "urn:cts:greekLit:tlg0085.tlg004:417", "start": 13013, "length": 32}, {"loc": "urn:cts:greekLit:tlg0085.tlg004:418", "start": 13045, "length": 30}, {"loc": "urn:cts:greekLit:tlg0085.tlg004:419", "start": 13075, "length": 35}, {"loc": "urn:cts:greekLit:tlg0085.tlg004:420", "start": 13110, "length": 25}, {"loc": "urn:cts:greekLit:tlg0085.tlg004:421", "start": 13135, "length": 18}, {"loc": "urn:cts:greekLit:tlg0085.tlg004:422", "start": 13153, "length": 37}, {"loc": "urn:cts:greekLit:tlg0085.tlg004:423", "start": 13190, "length": 44}, {"loc": "urn:cts:greekLit:tlg0085.tlg004:424", "start": 13234, "length": 37}, {"loc": "urn:cts:greekLit:tlg0085.tlg004:425", "start": 13271, "length": 45}, {"loc": "urn:cts:greekLit:tlg0085.tlg004:426", "start": 13316, "length": 45}, {"loc": "urn:cts:greekLit:tlg0085.tlg004:427", "start": 13361, "length": 37}, {"loc": "urn:cts:greekLit:tlg0085.tlg004:428", "start": 13398, "length": 37}, {"loc": "urn:cts:greekLit:tlg0085.tlg004:429", "start": 13435, "length": 37}, {"loc": "urn:cts:greekLit:tlg0085.tlg004:430", "start": 13472, "length": 40}, {"loc": "urn:cts:greekLit:tlg0085.tlg004:431", "start": 13512, "length": 35}, {"loc": "urn:cts:greekLit:tlg0085.tlg004:432", "start": 13547, "length": 36}, {"loc": "urn:cts:greekLit:tlg0085.tlg004:433", "start": 13583, "length": 38}, {"loc": "urn:cts:greekLit:tlg0085.tlg004:434", "start": 13621, "length": 40}, {"loc": "urn:cts:greekLit:tlg0085.tlg004:435", "start": 13661, "length": 34}, {"loc": "urn:cts:greekLit:tlg0085.tlg004:436", "start": 13695, "length": 38}, {"loc": "urn:cts:greekLit:tlg0085.tlg004:437", "start": 13733, "length": 38}, {"loc": "urn:cts:greekLit:tlg0085.tlg004:438", "start": 13771, "length": 36}, {"loc": "urn:cts:greekLit:tlg0085.tlg004:439", "start": 13807, "length": 36}, {"loc": "urn:cts:greekLit:tlg0085.tlg004:440", "start": 13843, "length": 43}, {"loc": "urn:cts:greekLit:tlg0085.tlg004:441", "start": 13886, "length": 33}, {"loc": "urn:cts:greekLit:tlg0085.tlg004:442", "start": 13919, "length": 34}, {"loc": "urn:cts:greekLit:tlg0085.tlg004:443", "start": 13953, "length": 35}, {"loc": "urn:cts:greekLit:tlg0085.tlg004:444", "start": 13988, "length": 38}, {"loc": "urn:cts:greekLit:tlg0085.tlg004:445", "start": 14026, "length": 34}, {"loc": "urn:cts:greekLit:tlg0085.tlg004:446", "start": 14060, "length": 35}, {"loc": "urn:cts:greekLit:tlg0085.tlg004:447", "start": 14095, "length": 43}, {"loc": "urn:cts:greekLit:tlg0085.tlg004:448", "start": 14138, "length": 37}, {"loc": "urn:cts:greekLit:tlg0085.tlg004:449", "start": 14175, "length": 33}, {"loc": "urn:cts:greekLit:tlg0085.tlg004:450", "start": 14208, "length": 41}, {"loc": "urn:cts:greekLit:tlg0085.tlg004:451", "start": 14249, "length": 38}, {"loc": "urn:cts:greekLit:tlg0085.tlg004:452", "start": 14287, "length": 34}, {"loc": "urn:cts:greekLit:tlg0085.tlg004:453", "start": 14321, "length": 33}, {"loc": "urn:cts:greekLit:tlg0085.tlg004:454", "start": 14354, "length": 34}, {"loc": "urn:cts:greekLit:tlg0085.tlg004:455", "start": 14388, "length": 20}, {"loc": "urn:cts:greekLit:tlg0085.tlg004:456", "start": 14408, "length": 21}, {"loc": "urn:cts:greekLit:tlg0085.tlg004:457", "start": 14429, "length": 41}, {"loc": "urn:cts:greekLit:tlg0085.tlg004:458", "start": 14470, "length": 37}, {"loc": "urn:cts:greekLit:tlg0085.tlg004:459", "start": 14507, "length": 37}, {"loc": "urn:cts:greekLit:tlg0085.tlg004:460", "start": 14544, "length": 35}, {"loc": "urn:cts:greekLit:tlg0085.tlg004:461", "start": 14579, "length": 38}, {"loc": "urn:cts:greekLit:tlg0085.tlg004:462", "start": 14617, "length": 40}, {"loc": "urn:cts:greekLit:tlg0085.tlg004:463", "start": 14657, "length": 36}, {"loc": "urn:cts:greekLit:tlg0085.tlg004:464", "start": 14693, "length": 38}, {"loc": "urn:cts:greekLit:tlg0085.tlg004:465", "start": 14731, "length": 41}, {"loc": "urn:cts:greekLit:tlg0085.tlg004:466", "start": 14772, "length": 39}, {"loc": "urn:cts:greekLit:tlg0085.tlg004:467", "start": 14811, "length": 44}, {"loc": "urn:cts:greekLit:tlg0085.tlg004:468", "start": 14855, "length": 38}, {"loc": "urn:cts:greekLit:tlg0085.tlg004:469", "start": 14893, "length": 40}, {"loc": "urn:cts:greekLit:tlg0085.tlg004:470", "start": 14933, "length": 34}, {"loc": "urn:cts:greekLit:tlg0085.tlg004:471", "start": 14967, "length": 38}, {"loc": "urn:cts:greekLit:tlg0085.tlg004:472", "start": 15005, "length": 39}, {"loc": "urn:cts:greekLit:tlg0085.tlg004:473", "start": 15044, "length": 40}, {"loc": "urn:cts:greekLit:tlg0085.tlg004:474", "start": 15084, "length": 38}, {"loc": "urn:cts:greekLit:tlg0085.tlg004:474b", "start": 15122, "length": 8}, {"loc": "urn:cts:greekLit:tlg0085.tlg004:475", "start": 15130, "length": 34}, {"loc": "urn:cts:greekLit:tlg0085.tlg004:476", "start": 15164, "length": 36}, {"loc": "urn:cts:greekLit:tlg0085.tlg004:477", "start": 15200, "length": 37}, {"loc": "urn:cts:greekLit:tlg0085.tlg004:478", "start": 15237, "length": 40}, {"loc": "urn:cts:greekLit:tlg0085.tlg004:479", "start": 15277, "length": 36}, {"loc": "urn:cts:greekLit:tlg0085.tlg004:480", "start": 15313, "length": 41}, {"loc": "urn:cts:greekLit:tlg0085.tlg004:481", "start": 15354, "length": 32}, {"loc": "urn:cts:greekLit:tlg0085.tlg004:482", "start": 15386, "length": 40}, {"loc": "urn:cts:greekLit:tlg0085.tlg004:483", "start": 15426, "length": 35}, {"loc": "urn:cts:greekLit:tlg0085.tlg004:484", "start": 15461, "length": 25}, {"loc": "urn:cts:greekLit:tlg0085.tlg004:485", "start": 15486, "length": 30}, {"loc": "urn:cts:greekLit:tlg0085.tlg004:486", "start": 15516, "length": 36}, {"loc": "urn:cts:greekLit:tlg0085.tlg004:487", "start": 15552, "length": 34}, {"loc": "urn:cts:greekLit:tlg0085.tlg004:488", "start": 15586, "length": 36}, {"loc": "urn:cts:greekLit:tlg0085.tlg004:489", "start": 15622, "length": 36}, {"loc": "urn:cts:greekLit:tlg0085.tlg004:490", "start": 15658, "length": 34}, {"loc": "urn:cts:greekLit:tlg0085.tlg004:491", "start": 15692, "length": 39}, {"loc": "urn:cts:greekLit:tlg0085.tlg004:492", "start": 15731, "length": 37}, {"loc": "urn:cts:greekLit:tlg0085.tlg004:493", "start": 15768, "length": 32}, {"loc": "urn:cts:greekLit:tlg0085.tlg004:494", "start": 15800, "length": 37}, {"loc": "urn:cts:greekLit:tlg0085.tlg004:495", "start": 15837, "length": 38}, {"loc": "urn:cts:greekLit:tlg0085.tlg004:496", "start": 15875, "length": 36}, {"loc": "urn:cts:greekLit:tlg0085.tlg004:497", "start": 15911, "length": 36}, {"loc": "urn:cts:greekLit:tlg0085.tlg004:498", "start": 15947, "length": 40}, {"loc": "urn:cts:greekLit:tlg0085.tlg004:499", "start": 15987, "length": 35}, {"loc": "urn:cts:greekLit:tlg0085.tlg004:500", "start": 16022, "length": 38}, {"loc": "urn:cts:greekLit:tlg0085.tlg004:501", "start": 16060, "length": 40}, {"loc": "urn:cts:greekLit:tlg0085.tlg004:502", "start": 16100, "length": 41}, {"loc": "urn:cts:greekLit:tlg0085.tlg004:503", "start": 16141, "length": 37}, {"loc": "urn:cts:greekLit:tlg0085.tlg004:504", "start": 16178, "length": 35}, {"loc": "urn:cts:greekLit:tlg0085.tlg004:505", "start": 16213, "length": 36}, {"loc": "urn:cts:greekLit:tlg0085.tlg004:506", "start": 16249, "length": 35}, {"loc": "urn:cts:greekLit:tlg0085.tlg004:507", "start": 16284, "length": 40}, {"loc": "urn:cts:greekLit:tlg0085.tlg004:508", "start": 16324, "length": 37}, {"loc": "urn:cts:greekLit:tlg0085.tlg004:509", "start": 16361, "length": 37}, {"loc": "urn:cts:greekLit:tlg0085.tlg004:510", "start": 16398, "length": 36}, {"loc": "urn:cts:greekLit:tlg0085.tlg004:511", "start": 16434, "length": 39}, {"loc": "urn:cts:greekLit:tlg0085.tlg004:512", "start": 16473, "length": 34}, {"loc": "urn:cts:greekLit:tlg0085.tlg004:513", "start": 16507, "length": 40}, {"loc": "urn:cts:greekLit:tlg0085.tlg004:514", "start": 16547, "length": 35}, {"loc": "urn:cts:greekLit:tlg0085.tlg004:515", "start": 16582, "length": 35}, {"loc": "urn:cts:greekLit:tlg0085.tlg004:516", "start": 16617, "length": 47}, {"loc": "urn:cts:greekLit:tlg0085.tlg004:517", "start": 16664, "length": 35}, {"loc": "urn:cts:greekLit:tlg0085.tlg004:519", "start": 16699, "length": 40}, {"loc": "urn:cts:greekLit:tlg0085.tlg004:518", "start": 16739, "length": 34}, {"loc": "urn:cts:greekLit:tlg0085.tlg004:520", "start": 16773, "length": 41}, {"loc": "urn:cts:greekLit:tlg0085.tlg004:521", "start": 16814, "length": 37}, {"loc": "urn:cts:greekLit:tlg0085.tlg004:522", "start": 16851, "length": 34}, {"loc": "urn:cts:greekLit:tlg0085.tlg004:523", "start": 16885, "length": 40}, {"loc": "urn:cts:greekLit:tlg0085.tlg004:524", "start": 16925, "length": 20}, {"loc": "urn:cts:greekLit:tlg0085.tlg004:525", "start": 16945, "length": 29}, {"loc": "urn:cts:greekLit:tlg0085.tlg004:526", "start": 16974, "length": 39}, {"loc": "urn:cts:greekLit:tlg0085.tlg004:527", "start": 17013, "length": 41}, {"loc": "urn:cts:greekLit:tlg0085.tlg004:528", "start": 17054, "length": 38}, {"loc": "urn:cts:greekLit:tlg0085.tlg004:529", "start": 17092, "length": 37}, {"loc": "urn:cts:greekLit:tlg0085.tlg004:530", "start": 17129, "length": 38}, {"loc": "urn:cts:greekLit:tlg0085.tlg004:531", "start": 17167, "length": 33}, {"loc": "urn:cts:greekLit:tlg0085.tlg004:532", "start": 17200, "length": 35}, {"loc": "urn:cts:greekLit:tlg0085.tlg004:533", "start": 17235, "length": 38}, {"loc": "urn:cts:greekLit:tlg0085.tlg004:534", "start": 17273, "length": 37}, {"loc": "urn:cts:greekLit:tlg0085.tlg004:535", "start": 17310, "length": 38}, {"loc": "urn:cts:greekLit:tlg0085.tlg004:536", "start": 17348, "length": 35}, {"loc": "urn:cts:greekLit:tlg0085.tlg004:537", "start": 17383, "length": 43}, {"loc": "urn:cts:greekLit:tlg0085.tlg004:538", "start": 17426, "length": 39}, {"loc": "urn:cts:greekLit:tlg0085.tlg004:539", "start": 17465, "length": 35}, {"loc": "urn:cts:greekLit:tlg0085.tlg004:540", "start": 17500, "length": 35}, {"loc": "urn:cts:greekLit:tlg0085.tlg004:541", "start": 17535, "length": 34}, {"loc": "urn:cts:greekLit:tlg0085.tlg004:542", "start": 17569, "length": 41}, {"loc": "urn:cts:greekLit:tlg0085.tlg004:543", "start": 17610, "length": 37}, {"loc": "urn:cts:greekLit:tlg0085.tlg004:544", "start": 17647, "length": 42}, {"loc": "urn:cts:greekLit:tlg0085.tlg004:545", "start": 17689, "length": 38}, {"loc": "urn:cts:greekLit:tlg0085.tlg004:546", "start": 17727, "length": 42}, {"loc": "urn:cts:greekLit:tlg0085.tlg004:547", "start": 17769, "length": 38}, {"loc": "urn:cts:greekLit:tlg0085.tlg004:548", "start": 17807, "length": 41}, {"loc": "urn:cts:greekLit:tlg0085.tlg004:549", "start": 17848, "length": 42}, {"loc": "urn:cts:greekLit:tlg0085.tlg004:550", "start": 17890, "length": 38}, {"loc": "urn:cts:greekLit:tlg0085.tlg004:551", "start": 17928, "length": 38}, {"loc": "urn:cts:greekLit:tlg0085.tlg004:552", "start": 17966, "length": 36}, {"loc": "urn:cts:greekLit:tlg0085.tlg004:553", "start": 18002, "length": 41}, {"loc": "urn:cts:greekLit:tlg0085.tlg004:554", "start": 18043, "length": 39}, {"loc": "urn:cts:greekLit:tlg0085.tlg004:555", "start": 18082, "length": 36}, {"loc": "urn:cts:greekLit:tlg0085.tlg004:556", "start": 18118, "length": 35}, {"loc": "urn:cts:greekLit:tlg0085.tlg004:557", "start": 18153, "length": 34}, {"loc": "urn:cts:greekLit:tlg0085.tlg004:558", "start": 18187, "length": 38}, {"loc": "urn:cts:greekLit:tlg0085.tlg004:559", "start": 18225, "length": 35}, {"loc": "urn:cts:greekLit:tlg0085.tlg004:560", "start": 18260, "length": 35}, {"loc": "urn:cts:greekLit:tlg0085.tlg004:561", "start": 18295, "length": 40}, {"loc": "urn:cts:greekLit:tlg0085.tlg004:562", "start": 18335, "length": 35}, {"loc": "urn:cts:greekLit:tlg0085.tlg004:563", "start": 18370, "length": 28}, {"loc": "urn:cts:greekLit:tlg0085.tlg004:564", "start": 18398, "length": 35}, {"loc": "urn:cts:greekLit:tlg0085.tlg004:565", "start": 18433, "length": 27}, {"loc": "urn:cts:greekLit:tlg0085.tlg004:566", "start": 18460, "length": 25}, {"loc": "urn:cts:greekLit:tlg0085.tlg004:567", "start": 18485, "length": 27}, {"loc": "urn:cts:greekLit:tlg0085.tlg004:568", "start": 18512, "length": 38}, {"loc": "urn:cts:greekLit:tlg0085.tlg004:569", "start": 18550, "length": 40}, {"loc": "urn:cts:greekLit:tlg0085.tlg004:570", "start": 18590, "length": 36}, {"loc": "urn:cts:greekLit:tlg0085.tlg004:571", "start": 18626, "length": 33}, {"loc": "urn:cts:greekLit:tlg0085.tlg004:572", "start": 18659, "length": 39}, {"loc": "urn:cts:greekLit:tlg0085.tlg004:573", "start": 18698, "length": 37}, {"loc": "urn:cts:greekLit:tlg0085.tlg004:574", "start": 18735, "length": 34}, {"loc": "urn:cts:greekLit:tlg0085.tlg004:575", "start": 18769, "length": 37}, {"loc": "urn:cts:greekLit:tlg0085.tlg004:576", "start": 18806, "length": 39}, {"loc": "urn:cts:greekLit:tlg0085.tlg004:577", "start": 18845, "length": 35}, {"loc": "urn:cts:greekLit:tlg0085.tlg004:578", "start": 18880, "length": 40}, {"loc": "urn:cts:greekLit:tlg0085.tlg004:579", "start": 18920, "length": 38}, {"loc": "urn:cts:greekLit:tlg0085.tlg004:580", "start": 18958, "length": 36}, {"loc": "urn:cts:greekLit:tlg0085.tlg004:581", "start": 18994, "length": 41}, {"loc": "urn:cts:greekLit:tlg0085.tlg004:582", "start": 19035, "length": 38}, {"loc": "urn:cts:greekLit:tlg0085.tlg004:583", "start": 19073, "length": 40}, {"loc": "urn:cts:greekLit:tlg0085.tlg004:584", "start": 19113, "length": 37}, {"loc": "urn:cts:greekLit:tlg0085.tlg004:585", "start": 19150, "length": 36}, {"loc": "urn:cts:greekLit:tlg0085.tlg004:586", "start": 19186, "length": 35}, {"loc": "urn:cts:greekLit:tlg0085.tlg004:587", "start": 19221, "length": 32}, {"loc": "urn:cts:greekLit:tlg0085.tlg004:588", "start": 19253, "length": 37}, {"loc": "urn:cts:greekLit:tlg0085.tlg004:589", "start": 19290, "length": 35}, {"loc": "urn:cts:greekLit:tlg0085.tlg004:590", "start": 19325, "length": 37}, {"loc": "urn:cts:greekLit:tlg0085.tlg004:591", "start": 19362, "length": 40}, {"loc": "urn:cts:greekLit:tlg0085.tlg004:592", "start": 19402, "length": 41}, {"loc": "urn:cts:greekLit:tlg0085.tlg004:593", "start": 19443, "length": 38}, {"loc": "urn:cts:greekLit:tlg0085.tlg004:594", "start": 19481, "length": 37}, {"loc": "urn:cts:greekLit:tlg0085.tlg004:595", "start": 19518, "length": 35}, {"loc": "urn:cts:greekLit:tlg0085.tlg004:596", "start": 19553, "length": 39}, {"loc": "urn:cts:greekLit:tlg0085.tlg004:597", "start": 19592, "length": 39}, {"loc": "urn:cts:greekLit:tlg0085.tlg004:598", "start": 19631, "length": 36}, {"loc": "urn:cts:greekLit:tlg0085.tlg004:599", "start": 19667, "length": 38}, {"loc": "urn:cts:greekLit:tlg0085.tlg004:600", "start": 19705, "length": 35}, {"loc": "urn:cts:greekLit:tlg0085.tlg004:601", "start": 19740, "length": 34}, {"loc": "urn:cts:greekLit:tlg0085.tlg004:602", "start": 19774, "length": 36}, {"loc": "urn:cts:greekLit:tlg0085.tlg004:603", "start": 19810, "length": 36}, {"loc": "urn:cts:greekLit:tlg0085.tlg004:604", "start": 19846, "length": 35}, {"loc": "urn:cts:greekLit:tlg0085.tlg004:605", "start": 19881, "length": 35}, {"loc": "urn:cts:greekLit:tlg0085.tlg004:606", "start": 19916, "length": 35}, {"loc": "urn:cts:greekLit:tlg0085.tlg004:607", "start": 19951, "length": 35}, {"loc": "urn:cts:greekLit:tlg0085.tlg004:608", "start": 19986, "length": 37}, {"loc": "urn:cts:greekLit:tlg0085.tlg004:609", "start": 20023, "length": 39}, {"loc": "urn:cts:greekLit:tlg0085.tlg004:610", "start": 20062, "length": 36}, {"loc": "urn:cts:greekLit:tlg0085.tlg004:611", "start": 20098, "length": 36}, {"loc": "urn:cts:greekLit:tlg0085.tlg004:612", "start": 20134, "length": 36}, {"loc": "urn:cts:greekLit:tlg0085.tlg004:613", "start": 20170, "length": 41}, {"loc": "urn:cts:greekLit:tlg0085.tlg004:614", "start": 20211, "length": 34}, {"loc": "urn:cts:greekLit:tlg0085.tlg004:615", "start": 20245, "length": 40}, {"loc": "urn:cts:greekLit:tlg0085.tlg004:616", "start": 20285, "length": 33}, {"loc": "urn:cts:greekLit:tlg0085.tlg004:617", "start": 20318, "length": 39}, {"loc": "urn:cts:greekLit:tlg0085.tlg004:618", "start": 20357, "length": 35}, {"loc": "urn:cts:greekLit:tlg0085.tlg004:619", "start": 20392, "length": 35}, {"loc": "urn:cts:greekLit:tlg0085.tlg004:620", "start": 20427, "length": 39}, {"loc": "urn:cts:greekLit:tlg0085.tlg004:621", "start": 20466, "length": 32}, {"loc": "urn:cts:greekLit:tlg0085.tlg004:622", "start": 20498, "length": 40}, {"loc": "urn:cts:greekLit:tlg0085.tlg004:623", "start": 20538, "length": 37}, {"loc": "urn:cts:greekLit:tlg0085.tlg004:624", "start": 20575, "length": 36}, {"loc": "urn:cts:greekLit:tlg0085.tlg004:625", "start": 20611, "length": 38}, {"loc": "urn:cts:greekLit:tlg0085.tlg004:626", "start": 20649, "length": 28}, {"loc": "urn:cts:greekLit:tlg0085.tlg004:627", "start": 20677, "length": 35}, {"loc": "urn:cts:greekLit:tlg0085.tlg004:628", "start": 20712, "length": 33}, {"loc": "urn:cts:greekLit:tlg0085.tlg004:629", "start": 20745, "length": 29}, {"loc": "urn:cts:greekLit:tlg0085.tlg004:630", "start": 20774, "length": 30}, {"loc": "urn:cts:greekLit:tlg0085.tlg004:631", "start": 20804, "length": 41}, {"loc": "urn:cts:greekLit:tlg0085.tlg004:632", "start": 20845, "length": 38}, {"loc": "urn:cts:greekLit:tlg0085.tlg004:633", "start": 20883, "length": 34}, {"loc": "urn:cts:greekLit:tlg0085.tlg004:634", "start": 20917, "length": 37}, {"loc": "urn:cts:greekLit:tlg0085.tlg004:635", "start": 20954, "length": 30}, {"loc": "urn:cts:greekLit:tlg0085.tlg004:636", "start": 20984, "length": 41}, {"loc": "urn:cts:greekLit:tlg0085.tlg004:637", "start": 21025, "length": 34}, {"loc": "urn:cts:greekLit:tlg0085.tlg004:638", "start": 21059, "length": 39}, {"loc": "urn:cts:greekLit:tlg0085.tlg004:639", "start": 21098, "length": 35}, {"loc": "urn:cts:greekLit:tlg0085.tlg004:640", "start": 21133, "length": 34}, {"loc": "urn:cts:greekLit:tlg0085.tlg004:641", "start": 21167, "length": 39}, {"loc": "urn:cts:greekLit:tlg0085.tlg004:642", "start": 21206, "length": 34}, {"loc": "urn:cts:greekLit:tlg0085.tlg004:643", "start": 21240, "length": 35}, {"loc": "urn:cts:greekLit:tlg0085.tlg004:644", "start": 21275, "length": 37}, {"loc": "urn:cts:greekLit:tlg0085.tlg004:645", "start": 21312, "length": 33}, {"loc": "urn:cts:greekLit:tlg0085.tlg004:646", "start": 21345, "length": 40}, {"loc": "urn:cts:greekLit:tlg0085.tlg004:647", "start": 21385, "length": 38}, {"loc": "urn:cts:greekLit:tlg0085.tlg004:648", "start": 21423, "length": 36}, {"loc": "urn:cts:greekLit:tlg0085.tlg004:649", "start": 21459, "length": 34}, {"loc": "urn:cts:greekLit:tlg0085.tlg004:650", "start": 21493, "length": 42}, {"loc": "urn:cts:greekLit:tlg0085.tlg004:651", "start": 21535, "length": 34}, {"loc": "urn:cts:greekLit:tlg0085.tlg004:652", "start": 21569, "length": 43}, {"loc": "urn:cts:greekLit:tlg0085.tlg004:653", "start": 21612, "length": 36}, {"loc": "urn:cts:greekLit:tlg0085.tlg004:654", "start": 21648, "length": 34}, {"loc": "urn:cts:greekLit:tlg0085.tlg004:655", "start": 21682, "length": 37}, {"loc": "urn:cts:greekLit:tlg0085.tlg004:656", "start": 21719, "length": 41}, {"loc": "urn:cts:greekLit:tlg0085.tlg004:657", "start": 21760, "length": 34}, {"loc": "urn:cts:greekLit:tlg0085.tlg004:658", "start": 21794, "length": 35}, {"loc": "urn:cts:greekLit:tlg0085.tlg004:659", "start": 21829, "length": 37}, {"loc": "urn:cts:greekLit:tlg0085.tlg004:660", "start": 21866, "length": 36}, {"loc": "urn:cts:greekLit:tlg0085.tlg004:661", "start": 21902, "length": 38}, {"loc": "urn:cts:greekLit:tlg0085.tlg004:662", "start": 21940, "length": 38}, {"loc": "urn:cts:greekLit:tlg0085.tlg004:663", "start": 21978, "length": 44}, {"loc": "urn:cts:greekLit:tlg0085.tlg004:664", "start": 22022, "length": 39}, {"loc": "urn:cts:greekLit:tlg0085.tlg004:665", "start": 22061, "length": 39}, {"loc": "urn:cts:greekLit:tlg0085.tlg004:666", "start": 22100, "length": 36}, {"loc": "urn:cts:greekLit:tlg0085.tlg004:667", "start": 22136, "length": 31}, {"loc": "urn:cts:greekLit:tlg0085.tlg004:668", "start": 22167, "length": 36}, {"loc": "urn:cts:greekLit:tlg0085.tlg004:669", "start": 22203, "length": 38}, {"loc": "urn:cts:greekLit:tlg0085.tlg004:670", "start": 22241, "length": 34}, {"loc": "urn:cts:greekLit:tlg0085.tlg004:671", "start": 22275, "length": 36}, {"loc": "urn:cts:greekLit:tlg0085.tlg004:672", "start": 22311, "length": 37}, {"loc": "urn:cts:greekLit:tlg0085.tlg004:673", "start": 22348, "length": 37}, {"loc": "urn:cts:greekLit:tlg0085.tlg004:674", "start": 22385, "length": 38}, {"loc": "urn:cts:greekLit:tlg0085.tlg004:675", "start": 22423, "length": 41}, {"loc": "urn:cts:greekLit:tlg0085.tlg004:676", "start": 22464, "length": 40}, {"loc": "urn:cts:greekLit:tlg0085.tlg004:677", "start": 22504, "length": 40}, {"loc": "urn:cts:greekLit:tlg0085.tlg004:678", "start": 22544, "length": 34}, {"loc": "urn:cts:greekLit:tlg0085.tlg004:679", "start": 22578, "length": 37}, {"loc": "urn:cts:greekLit:tlg0085.tlg004:680", "start": 22615, "length": 38}, {"loc": "urn:cts:greekLit:tlg0085.tlg004:681", "start": 22653, "length": 44}, {"loc": "urn:cts:greekLit:tlg0085.tlg004:682", "start": 22697, "length": 36}, {"loc": "urn:cts:greekLit:tlg0085.tlg004:683", "start": 22733, "length": 37}, {"loc": "urn:cts:greekLit:tlg0085.tlg004:684", "start": 22770, "length": 37}, {"loc": "urn:cts:greekLit:tlg0085.tlg004:685", "start": 22807, "length": 40}, {"loc": "urn:cts:greekLit:tlg0085.tlg004:686", "start": 22847, "length": 38}, {"loc": "urn:cts:greekLit:tlg0085.tlg004:687", "start": 22885, "length": 36}, {"loc": "urn:cts:greekLit:tlg0085.tlg004:688", "start": 22921, "length": 21}, {"loc": "urn:cts:greekLit:tlg0085.tlg004:689", "start": 22942, "length": 38}, {"loc": "urn:cts:greekLit:tlg0085.tlg004:690", "start": 22980, "length": 34}, {"loc": "urn:cts:greekLit:tlg0085.tlg004:691", "start": 23014, "length": 35}, {"loc": "urn:cts:greekLit:tlg0085.tlg004:692", "start": 23049, "length": 32}, {"loc": "urn:cts:greekLit:tlg0085.tlg004:693", "start": 23081, "length": 36}, {"loc": "urn:cts:greekLit:tlg0085.tlg004:694", "start": 23117, "length": 21}, {"loc": "urn:cts:greekLit:tlg0085.tlg004:695", "start": 23138, "length": 39}, {"loc": "urn:cts:greekLit:tlg0085.tlg004:696", "start": 23177, "length": 37}, {"loc": "urn:cts:greekLit:tlg0085.tlg004:697", "start": 23214, "length": 39}, {"loc": "urn:cts:greekLit:tlg0085.tlg004:698", "start": 23253, "length": 38}, {"loc": "urn:cts:greekLit:tlg0085.tlg004:699", "start": 23291, "length": 39}, {"loc": "urn:cts:greekLit:tlg0085.tlg004:700", "start": 23330, "length": 33}, {"loc": "urn:cts:greekLit:tlg0085.tlg004:701", "start": 23363, "length": 22}, {"loc": "urn:cts:greekLit:tlg0085.tlg004:702", "start": 23385, "length": 32}, {"loc": "urn:cts:greekLit:tlg0085.tlg004:703", "start": 23417, "length": 39}, {"loc": "urn:cts:greekLit:tlg0085.tlg004:704", "start": 23456, "length": 40}, {"loc": "urn:cts:greekLit:tlg0085.tlg004:705", "start": 23496, "length": 36}, {"loc": "urn:cts:greekLit:tlg0085.tlg004:706", "start": 23532, "length": 33}, {"loc": "urn:cts:greekLit:tlg0085.tlg004:707", "start": 23565, "length": 32}, {"loc": "urn:cts:greekLit:tlg0085.tlg004:708", "start": 23597, "length": 26}, {"loc": "urn:cts:greekLit:tlg0085.tlg004:709", "start": 23623, "length": 33}, {"loc": "urn:cts:greekLit:tlg0085.tlg004:710", "start": 23656, "length": 37}, {"loc": "urn:cts:greekLit:tlg0085.tlg004:711", "start": 23693, "length": 34}, {"loc": "urn:cts:greekLit:tlg0085.tlg004:712", "start": 23727, "length": 39}, {"loc": "urn:cts:greekLit:tlg0085.tlg004:713", "start": 23766, "length": 40}, {"loc": "urn:cts:greekLit:tlg0085.tlg004:714", "start": 23806, "length": 45}, {"loc": "urn:cts:greekLit:tlg0085.tlg004:715", "start": 23851, "length": 40}, {"loc": "urn:cts:greekLit:tlg0085.tlg004:716", "start": 23891, "length": 37}, {"loc": "urn:cts:greekLit:tlg0085.tlg004:717", "start": 23928, "length": 43}, {"loc": "urn:cts:greekLit:tlg0085.tlg004:718", "start": 23971, "length": 39}, {"loc": "urn:cts:greekLit:tlg0085.tlg004:719", "start": 24010, "length": 36}, {"loc": "urn:cts:greekLit:tlg0085.tlg004:720", "start": 24046, "length": 23}, {"loc": "urn:cts:greekLit:tlg0085.tlg004:721", "start": 24069, "length": 23}, {"loc": "urn:cts:greekLit:tlg0085.tlg004:722", "start": 24092, "length": 20}, {"loc": "urn:cts:greekLit:tlg0085.tlg004:723", "start": 24112, "length": 23}, {"loc": "urn:cts:greekLit:tlg0085.tlg004:724", "start": 24135, "length": 23}, {"loc": "urn:cts:greekLit:tlg0085.tlg004:725", "start": 24158, "length": 30}, {"loc": "urn:cts:greekLit:tlg0085.tlg004:726", "start": 24188, "length": 32}, {"loc": "urn:cts:greekLit:tlg0085.tlg004:727", "start": 24220, "length": 26}, {"loc": "urn:cts:greekLit:tlg0085.tlg004:728", "start": 24246, "length": 24}, {"loc": "urn:cts:greekLit:tlg0085.tlg004:729", "start": 24270, "length": 22}, {"loc": "urn:cts:greekLit:tlg0085.tlg004:730", "start": 24292, "length": 25}, {"loc": "urn:cts:greekLit:tlg0085.tlg004:731", "start": 24317, "length": 23}, {"loc": "urn:cts:greekLit:tlg0085.tlg004:732", "start": 24340, "length": 33}, {"loc": "urn:cts:greekLit:tlg0085.tlg004:733", "start": 24373, "length": 29}, {"loc": "urn:cts:greekLit:tlg0085.tlg004:734", "start": 24402, "length": 22}, {"loc": "urn:cts:greekLit:tlg0085.tlg004:735", "start": 24424, "length": 20}, {"loc": "urn:cts:greekLit:tlg0085.tlg004:736", "start": 24444, "length": 19}, {"loc": "urn:cts:greekLit:tlg0085.tlg004:737", "start": 24463, "length": 25}, {"loc": "urn:cts:greekLit:tlg0085.tlg004:738", "start": 24488, "length": 24}, {"loc": "urn:cts:greekLit:tlg0085.tlg004:739", "start": 24512, "length": 23}, {"loc": "urn:cts:greekLit:tlg0085.tlg004:740", "start": 24535, "length": 24}, {"loc": "urn:cts:greekLit:tlg0085.tlg004:741", "start": 24559, "length": 23}, {"loc": "urn:cts:greekLit:tlg0085.tlg004:742", "start": 24582, "length": 19}, {"loc": "urn:cts:greekLit:tlg0085.tlg004:743", "start": 24601, "length": 21}, {"loc": "urn:cts:greekLit:tlg0085.tlg004:744", "start": 24622, "length": 26}, {"loc": "urn:cts:greekLit:tlg0085.tlg004:745", "start": 24648, "length": 21}, {"loc": "urn:cts:greekLit:tlg0085.tlg004:746", "start": 24669, "length": 22}, {"loc": "urn:cts:greekLit:tlg0085.tlg004:747", "start": 24691, "length": 21}, {"loc": "urn:cts:greekLit:tlg0085.tlg004:748", "start": 24712, "length": 27}, {"loc": "urn:cts:greekLit:tlg0085.tlg004:749", "start": 24739, "length": 23}, {"loc": "urn:cts:greekLit:tlg0085.tlg004:750", "start": 24762, "length": 31}, {"loc": "urn:cts:greekLit:tlg0085.tlg004:751", "start": 24793, "length": 25}, {"loc": "urn:cts:greekLit:tlg0085.tlg004:752", "start": 24818, "length": 23}, {"loc": "urn:cts:greekLit:tlg0085.tlg004:753", "start": 24841, "length": 18}, {"loc": "urn:cts:greekLit:tlg0085.tlg004:754", "start": 24859, "length": 29}, {"loc": "urn:cts:greekLit:tlg0085.tlg004:755", "start": 24888, "length": 18}, {"loc": "urn:cts:greekLit:tlg0085.tlg004:756", "start": 24906, "length": 22}, {"loc": "urn:cts:greekLit:tlg0085.tlg004:757", "start": 24928, "length": 20}, {"loc": "urn:cts:greekLit:tlg0085.tlg004:758", "start": 24948, "length": 34}, {"loc": "urn:cts:greekLit:tlg0085.tlg004:759", "start": 24982, "length": 30}, {"loc": "urn:cts:greekLit:tlg0085.tlg004:760", "start": 25012, "length": 27}, {"loc": "urn:cts:greekLit:tlg0085.tlg004:761", "start": 25039, "length": 21}, {"loc": "urn:cts:greekLit:tlg0085.tlg004:762", "start": 25060, "length": 26}, {"loc": "urn:cts:greekLit:tlg0085.tlg004:763", "start": 25086, "length": 25}, {"loc": "urn:cts:greekLit:tlg0085.tlg004:764", "start": 25111, "length": 25}, {"loc": "urn:cts:greekLit:tlg0085.tlg004:765", "start": 25136, "length": 18}, {"loc": "urn:cts:greekLit:tlg0085.tlg004:766", "start": 25154, "length": 28}, {"loc": "urn:cts:greekLit:tlg0085.tlg004:767", "start": 25182, "length": 31}, {"loc": "urn:cts:greekLit:tlg0085.tlg004:768", "start": 25213, "length": 24}, {"loc": "urn:cts:greekLit:tlg0085.tlg004:769", "start": 25237, "length": 27}, {"loc": "urn:cts:greekLit:tlg0085.tlg004:770", "start": 25264, "length": 16}, {"loc": "urn:cts:greekLit:tlg0085.tlg004:771", "start": 25280, "length": 22}, {"loc": "urn:cts:greekLit:tlg0085.tlg004:772", "start": 25302, "length": 34}, {"loc": "urn:cts:greekLit:tlg0085.tlg004:773", "start": 25336, "length": 28}, {"loc": "urn:cts:greekLit:tlg0085.tlg004:774", "start": 25364, "length": 26}, {"loc": "urn:cts:greekLit:tlg0085.tlg004:775", "start": 25390, "length": 25}, {"loc": "urn:cts:greekLit:tlg0085.tlg004:776", "start": 25415, "length": 16}, {"loc": "urn:cts:greekLit:tlg0085.tlg004:777", "start": 25431, "length": 21}, {"loc": "urn:cts:greekLit:tlg0085.tlg004:778", "start": 25452, "length": 17}, {"loc": "urn:cts:greekLit:tlg0085.tlg004:779", "start": 25469, "length": 22}, {"loc": "urn:cts:greekLit:tlg0085.tlg004:780", "start": 25491, "length": 26}, {"loc": "urn:cts:greekLit:tlg0085.tlg004:781", "start": 25517, "length": 17}, {"loc": "urn:cts:greekLit:tlg0085.tlg004:782", "start": 25534, "length": 22}, {"loc": "urn:cts:greekLit:tlg0085.tlg004:783", "start": 25556, "length": 19}, {"loc": "urn:cts:greekLit:tlg0085.tlg004:784", "start": 25575, "length": 32}, {"loc": "urn:cts:greekLit:tlg0085.tlg004:785", "start": 25607, "length": 18}, {"loc": "urn:cts:greekLit:tlg0085.tlg004:786", "start": 25625, "length": 25}, {"loc": "urn:cts:greekLit:tlg0085.tlg004:787", "start": 25650, "length": 26}, {"loc": "urn:cts:greekLit:tlg0085.tlg004:788", "start": 25676, "length": 19}, {"loc": "urn:cts:greekLit:tlg0085.tlg004:789", "start": 25695, "length": 21}, {"loc": "urn:cts:greekLit:tlg0085.tlg004:790", "start": 25716, "length": 21}, {"loc": "urn:cts:greekLit:tlg0085.tlg004:791", "start": 25737, "length": 28}, {"loc": "urn:cts:greekLit:tlg0085.tlg004:792", "start": 25765, "length": 38}, {"loc": "urn:cts:greekLit:tlg0085.tlg004:793", "start": 25803, "length": 34}, {"loc": "urn:cts:greekLit:tlg0085.tlg004:794", "start": 25837, "length": 36}, {"loc": "urn:cts:greekLit:tlg0085.tlg004:795", "start": 25873, "length": 35}, {"loc": "urn:cts:greekLit:tlg0085.tlg004:796", "start": 25908, "length": 37}, {"loc": "urn:cts:greekLit:tlg0085.tlg004:797", "start": 25945, "length": 39}, {"loc": "urn:cts:greekLit:tlg0085.tlg004:798", "start": 25984, "length": 36}, {"loc": "urn:cts:greekLit:tlg0085.tlg004:799", "start": 26020, "length": 39}, {"loc": "urn:cts:greekLit:tlg0085.tlg004:800", "start": 26059, "length": 36}, {"loc": "urn:cts:greekLit:tlg0085.tlg004:801", "start": 26095, "length": 35}, {"loc": "urn:cts:greekLit:tlg0085.tlg004:802", "start": 26130, "length": 34}, {"loc": "urn:cts:greekLit:tlg0085.tlg004:803", "start": 26164, "length": 40}, {"loc": "urn:cts:greekLit:tlg0085.tlg004:804", "start": 26204, "length": 39}, {"loc": "urn:cts:greekLit:tlg0085.tlg004:805", "start": 26243, "length": 42}, {"loc": "urn:cts:greekLit:tlg0085.tlg004:806", "start": 26285, "length": 38}, {"loc": "urn:cts:greekLit:tlg0085.tlg004:807", "start": 26323, "length": 39}, {"loc": "urn:cts:greekLit:tlg0085.tlg004:808", "start": 26362, "length": 36}, {"loc": "urn:cts:greekLit:tlg0085.tlg004:809", "start": 26398, "length": 43}, {"loc": "urn:cts:greekLit:tlg0085.tlg004:810", "start": 26441, "length": 37}, {"loc": "urn:cts:greekLit:tlg0085.tlg004:811", "start": 26478, "length": 38}, {"loc": "urn:cts:greekLit:tlg0085.tlg004:812", "start": 26516, "length": 38}, {"loc": "urn:cts:greekLit:tlg0085.tlg004:813", "start": 26554, "length": 38}, {"loc": "urn:cts:greekLit:tlg0085.tlg004:814", "start": 26592, "length": 37}, {"loc": "urn:cts:greekLit:tlg0085.tlg004:815", "start": 26629, "length": 42}, {"loc": "urn:cts:greekLit:tlg0085.tlg004:816", "start": 26671, "length": 35}, {"loc": "urn:cts:greekLit:tlg0085.tlg004:817", "start": 26706, "length": 33}, {"loc": "urn:cts:greekLit:tlg0085.tlg004:818", "start": 26739, "length": 37}, {"loc": "urn:cts:greekLit:tlg0085.tlg004:819", "start": 26776, "length": 40}, {"loc": "urn:cts:greekLit:tlg0085.tlg004:820", "start": 26816, "length": 40}, {"loc": "urn:cts:greekLit:tlg0085.tlg004:821", "start": 26856, "length": 36}, {"loc": "urn:cts:greekLit:tlg0085.tlg004:822", "start": 26892, "length": 27}, {"loc": "urn:cts:greekLit:tlg0085.tlg004:823", "start": 26919, "length": 31}, {"loc": "urn:cts:greekLit:tlg0085.tlg004:824", "start": 26950, "length": 15}, {"loc": "urn:cts:greekLit:tlg0085.tlg004:825", "start": 26965, "length": 25}, {"loc": "urn:cts:greekLit:tlg0085.tlg004:826", "start": 26990, "length": 26}, {"loc": "urn:cts:greekLit:tlg0085.tlg004:827", "start": 27016, "length": 32}, {"loc": "urn:cts:greekLit:tlg0085.tlg004:830", "start": 27048, "length": 29}, {"loc": "urn:cts:greekLit:tlg0085.tlg004:831", "start": 27077, "length": 29}, {"loc": "urn:cts:greekLit:tlg0085.tlg004:832", "start": 27106, "length": 16}, {"loc": "urn:cts:greekLit:tlg0085.tlg004:832b", "start": 27122, "length": 23}, {"loc": "urn:cts:greekLit:tlg0085.tlg004:833", "start": 27145, "length": 21}, {"loc": "urn:cts:greekLit:tlg0085.tlg004:833b", "start": 27166, "length": 23}, {"loc": "urn:cts:greekLit:tlg0085.tlg004:834", "start": 27189, "length": 38}, {"loc": "urn:cts:greekLit:tlg0085.tlg004:835", "start": 27227, "length": 19}, {"loc": "urn:cts:greekLit:tlg0085.tlg004:836", "start": 27246, "length": 20}, {"loc": "urn:cts:greekLit:tlg0085.tlg004:837", "start": 27266, "length": 25}, {"loc": "urn:cts:greekLit:tlg0085.tlg004:838", "start": 27291, "length": 24}, {"loc": "urn:cts:greekLit:tlg0085.tlg004:839", "start": 27315, "length": 19}, {"loc": "urn:cts:greekLit:tlg0085.tlg004:840", "start": 27334, "length": 24}, {"loc": "urn:cts:greekLit:tlg0085.tlg004:841", "start": 27358, "length": 24}, {"loc": "urn:cts:greekLit:tlg0085.tlg004:842", "start": 27382, "length": 35}, {"loc": "urn:cts:greekLit:tlg0085.tlg004:843", "start": 27417, "length": 24}, {"loc": "urn:cts:greekLit:tlg0085.tlg004:844", "start": 27441, "length": 24}, {"loc": "urn:cts:greekLit:tlg0085.tlg004:845", "start": 27465, "length": 24}, {"loc": "urn:cts:greekLit:tlg0085.tlg004:846", "start": 27489, "length": 29}, {"loc": "urn:cts:greekLit:tlg0085.tlg004:847", "start": 27518, "length": 21}, {"loc": "urn:cts:greekLit:tlg0085.tlg004:848", "start": 27539, "length": 39}, {"loc": "urn:cts:greekLit:tlg0085.tlg004:849", "start": 27578, "length": 28}, {"loc": "urn:cts:greekLit:tlg0085.tlg004:850", "start": 27606, "length": 27}, {"loc": "urn:cts:greekLit:tlg0085.tlg004:851", "start": 27633, "length": 23}, {"loc": "urn:cts:greekLit:tlg0085.tlg004:852", "start": 27656, "length": 28}, {"loc": "urn:cts:greekLit:tlg0085.tlg004:853", "start": 27684, "length": 16}, {"loc": "urn:cts:greekLit:tlg0085.tlg004:854", "start": 27700, "length": 31}, {"loc": "urn:cts:greekLit:tlg0085.tlg004:855", "start": 27731, "length": 36}, {"loc": "urn:cts:greekLit:tlg0085.tlg004:856", "start": 27767, "length": 40}, {"loc": "urn:cts:greekLit:tlg0085.tlg004:857", "start": 27807, "length": 43}, {"loc": "urn:cts:greekLit:tlg0085.tlg004:858", "start": 27850, "length": 33}, {"loc": "urn:cts:greekLit:tlg0085.tlg004:860", "start": 27883, "length": 30}, {"loc": "urn:cts:greekLit:tlg0085.tlg004:861", "start": 27913, "length": 32}, {"loc": "urn:cts:greekLit:tlg0085.tlg004:862", "start": 27945, "length": 31}, {"loc": "urn:cts:greekLit:tlg0085.tlg004:863", "start": 27976, "length": 31}, {"loc": "urn:cts:greekLit:tlg0085.tlg004:864", "start": 28007, "length": 31}, {"loc": "urn:cts:greekLit:tlg0085.tlg004:865", "start": 28038, "length": 29}, {"loc": "urn:cts:greekLit:tlg0085.tlg004:866", "start": 28067, "length": 28}, {"loc": "urn:cts:greekLit:tlg0085.tlg004:867", "start": 28095, "length": 32}, {"loc": "urn:cts:greekLit:tlg0085.tlg004:868", "start": 28127, "length": 15}, {"loc": "urn:cts:greekLit:tlg0085.tlg004:870", "start": 28142, "length": 26}, {"loc": "urn:cts:greekLit:tlg0085.tlg004:871", "start": 28168, "length": 32}, {"loc": "urn:cts:greekLit:tlg0085.tlg004:872", "start": 28200, "length": 31}, {"loc": "urn:cts:greekLit:tlg0085.tlg004:873", "start": 28231, "length": 34}, {"loc": "urn:cts:greekLit:tlg0085.tlg004:874", "start": 28265, "length": 33}, {"loc": "urn:cts:greekLit:tlg0085.tlg004:875", "start": 28298, "length": 17}, {"loc": "urn:cts:greekLit:tlg0085.tlg004:876", "start": 28315, "length": 35}, {"loc": "urn:cts:greekLit:tlg0085.tlg004:877", "start": 28350, "length": 22}, {"loc": "urn:cts:greekLit:tlg0085.tlg004:878", "start": 28372, "length": 22}, {"loc": "urn:cts:greekLit:tlg0085.tlg004:879", "start": 28394, "length": 32}, {"loc": "urn:cts:greekLit:tlg0085.tlg004:880", "start": 28426, "length": 24}, {"loc": "urn:cts:greekLit:tlg0085.tlg004:881", "start": 28450, "length": 14}, {"loc": "urn:cts:greekLit:tlg0085.tlg004:882", "start": 28464, "length": 34}, {"loc": "urn:cts:greekLit:tlg0085.tlg004:883", "start": 28498, "length": 19}, {"loc": "urn:cts:greekLit:tlg0085.tlg004:885", "start": 28517, "length": 18}, {"loc": "urn:cts:greekLit:tlg0085.tlg004:886", "start": 28535, "length": 31}, {"loc": "urn:cts:greekLit:tlg0085.tlg004:887", "start": 28566, "length": 25}, {"loc": "urn:cts:greekLit:tlg0085.tlg004:888", "start": 28591, "length": 25}, {"loc": "urn:cts:greekLit:tlg0085.tlg004:889", "start": 28616, "length": 17}, {"loc": "urn:cts:greekLit:tlg0085.tlg004:890", "start": 28633, "length": 28}, {"loc": "urn:cts:greekLit:tlg0085.tlg004:891", "start": 28661, "length": 1}, {"loc": "urn:cts:greekLit:tlg0085.tlg004:892", "start": 28662, "length": 16}, {"loc": "urn:cts:greekLit:tlg0085.tlg004:893", "start": 28678, "length": 18}, {"loc": "urn:cts:greekLit:tlg0085.tlg004:894", "start": 28696, "length": 14}, {"loc": "urn:cts:greekLit:tlg0085.tlg004:895", "start": 28710, "length": 36}, {"loc": "urn:cts:greekLit:tlg0085.tlg004:896", "start": 28746, "length": 29}, {"loc": "urn:cts:greekLit:tlg0085.tlg004:897", "start": 28775, "length": 15}, {"loc": "urn:cts:greekLit:tlg0085.tlg004:898", "start": 28790, "length": 19}, {"loc": "urn:cts:greekLit:tlg0085.tlg004:899", "start": 28809, "length": 20}, {"loc": "urn:cts:greekLit:tlg0085.tlg004:900", "start": 28829, "length": 28}, {"loc": "urn:cts:greekLit:tlg0085.tlg004:901", "start": 28857, "length": 17}, {"loc": "urn:cts:greekLit:tlg0085.tlg004:902", "start": 28874, "length": 30}, {"loc": "urn:cts:greekLit:tlg0085.tlg004:903", "start": 28904, "length": 21}, {"loc": "urn:cts:greekLit:tlg0085.tlg004:904", "start": 28925, "length": 19}, {"loc": "urn:cts:greekLit:tlg0085.tlg004:905", "start": 28944, "length": 18}, {"loc": "urn:cts:greekLit:tlg0085.tlg004:906", "start": 28962, "length": 19}, {"loc": "urn:cts:greekLit:tlg0085.tlg004:907", "start": 28981, "length": 26}, {"loc": "urn:cts:greekLit:tlg0085.tlg004:908", "start": 29007, "length": 27}, {"loc": "urn:cts:greekLit:tlg0085.tlg004:909", "start": 29034, "length": 19}, {"loc": "urn:cts:greekLit:tlg0085.tlg004:909b", "start": 29053, "length": 17}, {"loc": "urn:cts:greekLit:tlg0085.tlg004:910", "start": 29070, "length": 20}, {"loc": "urn:cts:greekLit:tlg0085.tlg004:911", "start": 29090, "length": 31}, {"loc": "urn:cts:greekLit:tlg0085.tlg004:912", "start": 29121, "length": 31}, {"loc": "urn:cts:greekLit:tlg0085.tlg004:913", "start": 29152, "length": 26}, {"loc": "urn:cts:greekLit:tlg0085.tlg004:914", "start": 29178, "length": 21}, {"loc": "urn:cts:greekLit:tlg0085.tlg004:915", "start": 29199, "length": 26}, {"loc": "urn:cts:greekLit:tlg0085.tlg004:916", "start": 29225, "length": 27}, {"loc": "urn:cts:greekLit:tlg0085.tlg004:917", "start": 29252, "length": 21}, {"loc": "urn:cts:greekLit:tlg0085.tlg004:918", "start": 29273, "length": 35}, {"loc": "urn:cts:greekLit:tlg0085.tlg004:919", "start": 29308, "length": 23}, {"loc": "urn:cts:greekLit:tlg0085.tlg004:920", "start": 29331, "length": 23}, {"loc": "urn:cts:greekLit:tlg0085.tlg004:921", "start": 29354, "length": 23}, {"loc": "urn:cts:greekLit:tlg0085.tlg004:922", "start": 29377, "length": 32}, {"loc": "urn:cts:greekLit:tlg0085.tlg004:923", "start": 29409, "length": 30}, {"loc": "urn:cts:greekLit:tlg0085.tlg004:924", "start": 29439, "length": 23}, {"loc": "urn:cts:greekLit:tlg0085.tlg004:925", "start": 29462, "length": 20}, {"loc": "urn:cts:greekLit:tlg0085.tlg004:926", "start": 29482, "length": 25}, {"loc": "urn:cts:greekLit:tlg0085.tlg004:927", "start": 29507, "length": 26}, {"loc": "urn:cts:greekLit:tlg0085.tlg004:928", "start": 29533, "length": 22}, {"loc": "urn:cts:greekLit:tlg0085.tlg004:929", "start": 29555, "length": 34}, {"loc": "urn:cts:greekLit:tlg0085.tlg004:930", "start": 29589, "length": 32}, {"loc": "urn:cts:greekLit:tlg0085.tlg004:931", "start": 29621, "length": 23}, {"loc": "urn:cts:greekLit:tlg0085.tlg004:932", "start": 29644, "length": 21}, {"loc": "urn:cts:greekLit:tlg0085.tlg004:933", "start": 29665, "length": 31}, {"loc": "urn:cts:greekLit:tlg0085.tlg004:934", "start": 29696, "length": 21}, {"loc": "urn:cts:greekLit:tlg0085.tlg004:935", "start": 29717, "length": 17}, {"loc": "urn:cts:greekLit:tlg0085.tlg004:936", "start": 29734, "length": 20}, {"loc": "urn:cts:greekLit:tlg0085.tlg004:937", "start": 29754, "length": 30}, {"loc": "urn:cts:greekLit:tlg0085.tlg004:938", "start": 29784, "length": 13}, {"loc": "urn:cts:greekLit:tlg0085.tlg004:939", "start": 29797, "length": 34}, {"loc": "urn:cts:greekLit:tlg0085.tlg004:940", "start": 29831, "length": 31}, {"loc": "urn:cts:greekLit:tlg0085.tlg004:941", "start": 29862, "length": 23}, {"loc": "urn:cts:greekLit:tlg0085.tlg004:942", "start": 29885, "length": 35}, {"loc": "urn:cts:greekLit:tlg0085.tlg004:943", "start": 29920, "length": 31}, {"loc": "urn:cts:greekLit:tlg0085.tlg004:944", "start": 29951, "length": 17}, {"loc": "urn:cts:greekLit:tlg0085.tlg004:945", "start": 29968, "length": 33}, {"loc": "urn:cts:greekLit:tlg0085.tlg004:946", "start": 30001, "length": 17}, {"loc": "urn:cts:greekLit:tlg0085.tlg004:947", "start": 30018, "length": 18}, {"loc": "urn:cts:greekLit:tlg0085.tlg004:948", "start": 30036, "length": 23}, {"loc": "urn:cts:greekLit:tlg0085.tlg004:949", "start": 30059, "length": 24}, {"loc": "urn:cts:greekLit:tlg0085.tlg004:950", "start": 30083, "length": 16}, {"loc": "urn:cts:greekLit:tlg0085.tlg004:951", "start": 30099, "length": 25}, {"loc": "urn:cts:greekLit:tlg0085.tlg004:952", "start": 30124, "length": 33}, {"loc": "urn:cts:greekLit:tlg0085.tlg004:953", "start": 30157, "length": 22}, {"loc": "urn:cts:greekLit:tlg0085.tlg004:954", "start": 30179, "length": 35}, {"loc": "urn:cts:greekLit:tlg0085.tlg004:955", "start": 30214, "length": 35}, {"loc": "urn:cts:greekLit:tlg0085.tlg004:956", "start": 30249, "length": 18}, {"loc": "urn:cts:greekLit:tlg0085.tlg004:957", "start": 30267, "length": 18}, {"loc": "urn:cts:greekLit:tlg0085.tlg004:957b", "start": 30285, "length": 25}, {"loc": "urn:cts:greekLit:tlg0085.tlg004:958", "start": 30310, "length": 16}, {"loc": "urn:cts:greekLit:tlg0085.tlg004:959", "start": 30326, "length": 16}, {"loc": "urn:cts:greekLit:tlg0085.tlg004:960", "start": 30342, "length": 12}, {"loc": "urn:cts:greekLit:tlg0085.tlg004:961", "start": 30354, "length": 12}, {"loc": "urn:cts:greekLit:tlg0085.tlg004:962", "start": 30366, "length": 10}, {"loc": "urn:cts:greekLit:tlg0085.tlg004:963", "start": 30376, "length": 11}, {"loc": "urn:cts:greekLit:tlg0085.tlg004:964", "start": 30387, "length": 12}, {"loc": "urn:cts:greekLit:tlg0085.tlg004:965", "start": 30399, "length": 10}, {"loc": "urn:cts:greekLit:tlg0085.tlg004:966", "start": 30409, "length": 4}, {"loc": "urn:cts:greekLit:tlg0085.tlg004:966b", "start": 30413, "length": 4}, {"loc": "urn:cts:greekLit:tlg0085.tlg004:967", "start": 30417, "length": 22}, {"loc": "urn:cts:greekLit:tlg0085.tlg004:968", "start": 30439, "length": 24}, {"loc": "urn:cts:greekLit:tlg0085.tlg004:969", "start": 30463, "length": 19}, {"loc": "urn:cts:greekLit:tlg0085.tlg004:970", "start": 30482, "length": 25}, {"loc": "urn:cts:greekLit:tlg0085.tlg004:971", "start": 30507, "length": 23}, {"loc": "urn:cts:greekLit:tlg0085.tlg004:972", "start": 30530, "length": 19}, {"loc": "urn:cts:greekLit:tlg0085.tlg004:973", "start": 30549, "length": 14}, {"loc": "urn:cts:greekLit:tlg0085.tlg004:974", "start": 30563, "length": 15}, {"loc": "urn:cts:greekLit:tlg0085.tlg004:975", "start": 30578, "length": 26}, {"loc": "urn:cts:greekLit:tlg0085.tlg004:976", "start": 30604, "length": 24}, {"loc": "urn:cts:greekLit:tlg0085.tlg004:977", "start": 30628, "length": 29}, {"loc": "urn:cts:greekLit:tlg0085.tlg004:978", "start": 30657, "length": 24}, {"loc": "urn:cts:greekLit:tlg0085.tlg004:979", "start": 30681, "length": 37}, {"loc": "urn:cts:greekLit:tlg0085.tlg004:980", "start": 30718, "length": 4}, {"loc": "urn:cts:greekLit:tlg0085.tlg004:980b", "start": 30722, "length": 4}, {"loc": "urn:cts:greekLit:tlg0085.tlg004:981", "start": 30726, "length": 18}, {"loc": "urn:cts:greekLit:tlg0085.tlg004:982", "start": 30744, "length": 23}, {"loc": "urn:cts:greekLit:tlg0085.tlg004:983", "start": 30767, "length": 26}, {"loc": "urn:cts:greekLit:tlg0085.tlg004:984", "start": 30793, "length": 27}, {"loc": "urn:cts:greekLit:tlg0085.tlg004:985", "start": 30820, "length": 17}, {"loc": "urn:cts:greekLit:tlg0085.tlg004:986", "start": 30837, "length": 19}, {"loc": "urn:cts:greekLit:tlg0085.tlg004:987", "start": 30856, "length": 13}, {"loc": "urn:cts:greekLit:tlg0085.tlg004:988", "start": 30869, "length": 13}, {"loc": "urn:cts:greekLit:tlg0085.tlg004:989", "start": 30882, "length": 24}, {"loc": "urn:cts:greekLit:tlg0085.tlg004:990", "start": 30906, "length": 26}, {"loc": "urn:cts:greekLit:tlg0085.tlg004:991", "start": 30932, "length": 29}, {"loc": "urn:cts:greekLit:tlg0085.tlg004:992", "start": 30961, "length": 24}, {"loc": "urn:cts:greekLit:tlg0085.tlg004:993", "start": 30985, "length": 37}, {"loc": "urn:cts:greekLit:tlg0085.tlg004:994", "start": 31022, "length": 27}, {"loc": "urn:cts:greekLit:tlg0085.tlg004:995", "start": 31049, "length": 27}, {"loc": "urn:cts:greekLit:tlg0085.tlg004:996", "start": 31076, "length": 24}, {"loc": "urn:cts:greekLit:tlg0085.tlg004:997", "start": 31100, "length": 25}, {"loc": "urn:cts:greekLit:tlg0085.tlg004:998", "start": 31125, "length": 13}, {"loc": "urn:cts:greekLit:tlg0085.tlg004:999", "start": 31138, "length": 14}, {"loc": "urn:cts:greekLit:tlg0085.tlg004:1000", "start": 31152, "length": 10}, {"loc": "urn:cts:greekLit:tlg0085.tlg004:1001", "start": 31162, "length": 9}, {"loc": "urn:cts:greekLit:tlg0085.tlg004:1002", "start": 31171, "length": 18}, {"loc": "urn:cts:greekLit:tlg0085.tlg004:1003", "start": 31189, "length": 20}, {"loc": "urn:cts:greekLit:tlg0085.tlg004:1004", "start": 31209, "length": 22}, {"loc": "urn:cts:greekLit:tlg0085.tlg004:1005", "start": 31231, "length": 28}, {"loc": "urn:cts:greekLit:tlg0085.tlg004:1006", "start": 31259, "length": 26}, {"loc": "urn:cts:greekLit:tlg0085.tlg004:1007", "start": 31285, "length": 23}, {"loc": "urn:cts:greekLit:tlg0085.tlg004:1008", "start": 31308, "length": 31}, {"loc": "urn:cts:greekLit:tlg0085.tlg004:1009", "start": 31339, "length": 27}, {"loc": "urn:cts:greekLit:tlg0085.tlg004:1010", "start": 31366, "length": 28}, {"loc": "urn:cts:greekLit:tlg0085.tlg004:1011", "start": 31394, "length": 40}, {"loc": "urn:cts:greekLit:tlg0085.tlg004:1012", "start": 31434, "length": 40}, {"loc": "urn:cts:greekLit:tlg0085.tlg004:1013", "start": 31474, "length": 37}, {"loc": "urn:cts:greekLit:tlg0085.tlg004:1014", "start": 31511, "length": 38}, {"loc": "urn:cts:greekLit:tlg0085.tlg004:1015", "start": 31549, "length": 43}, {"loc": "urn:cts:greekLit:tlg0085.tlg004:1016", "start": 31592, "length": 38}, {"loc": "urn:cts:greekLit:tlg0085.tlg004:1017", "start": 31630, "length": 42}, {"loc": "urn:cts:greekLit:tlg0085.tlg004:1018", "start": 31672, "length": 39}, {"loc": "urn:cts:greekLit:tlg0085.tlg004:1019", "start": 31711, "length": 43}, {"loc": "urn:cts:greekLit:tlg0085.tlg004:1020", "start": 31754, "length": 35}, {"loc": "urn:cts:greekLit:tlg0085.tlg004:1021", "start": 31789, "length": 36}, {"loc": "urn:cts:greekLit:tlg0085.tlg004:1022", "start": 31825, "length": 33}, {"loc": "urn:cts:greekLit:tlg0085.tlg004:1023", "start": 31858, "length": 40}, {"loc": "urn:cts:greekLit:tlg0085.tlg004:1024", "start": 31898, "length": 31}, {"loc": "urn:cts:greekLit:tlg0085.tlg004:1025", "start": 31929, "length": 38}, {"loc": "urn:cts:greekLit:tlg0085.tlg004:1026", "start": 31967, "length": 36}, {"loc": "urn:cts:greekLit:tlg0085.tlg004:1027", "start": 32003, "length": 35}, {"loc": "urn:cts:greekLit:tlg0085.tlg004:1028", "start": 32038, "length": 37}, {"loc": "urn:cts:greekLit:tlg0085.tlg004:1029", "start": 32075, "length": 39}, {"loc": "urn:cts:greekLit:tlg0085.tlg004:1030", "start": 32114, "length": 35}, {"loc": "urn:cts:greekLit:tlg0085.tlg004:1031", "start": 32149, "length": 35}, {"loc": "urn:cts:greekLit:tlg0085.tlg004:1032", "start": 32184, "length": 36}, {"loc": "urn:cts:greekLit:tlg0085.tlg004:1033", "start": 32220, "length": 39}, {"loc": "urn:cts:greekLit:tlg0085.tlg004:1034", "start": 32259, "length": 32}, {"loc": "urn:cts:greekLit:tlg0085.tlg004:1035", "start": 32291, "length": 41}, {"loc": "urn:cts:greekLit:tlg0085.tlg004:1036", "start": 32332, "length": 37}, {"loc": "urn:cts:greekLit:tlg0085.tlg004:1037", "start": 32369, "length": 42}, {"loc": "urn:cts:greekLit:tlg0085.tlg004:1038", "start": 32411, "length": 38}, {"loc": "urn:cts:greekLit:tlg0085.tlg004:1039", "start": 32449, "length": 37}, {"loc": "urn:cts:greekLit:tlg0085.tlg004:1040", "start": 32486, "length": 34}, {"loc": "urn:cts:greekLit:tlg0085.tlg004:1041", "start": 32520, "length": 36}, {"loc": "urn:cts:greekLit:tlg0085.tlg004:1042", "start": 32556, "length": 35}, {"loc": "urn:cts:greekLit:tlg0085.tlg004:1043", "start": 32591, "length": 35}, {"loc": "urn:cts:greekLit:tlg0085.tlg004:1044", "start": 32626, "length": 33}, {"loc": "urn:cts:greekLit:tlg0085.tlg004:1045", "start": 32659, "length": 35}, {"loc": "urn:cts:greekLit:tlg0085.tlg004:1046", "start": 32694, "length": 34}, {"loc": "urn:cts:greekLit:tlg0085.tlg004:1047", "start": 32728, "length": 36}, {"loc": "urn:cts:greekLit:tlg0085.tlg004:1048", "start": 32764, "length": 33}, {"loc": "urn:cts:greekLit:tlg0085.tlg004:1049", "start": 32797, "length": 35}, {"loc": "urn:cts:greekLit:tlg0085.tlg004:1050", "start": 32832, "length": 37}, {"loc": "urn:cts:greekLit:tlg0085.tlg004:1051", "start": 32869, "length": 40}, {"loc": "urn:cts:greekLit:tlg0085.tlg004:1052", "start": 32909, "length": 41}, {"loc": "urn:cts:greekLit:tlg0085.tlg004:1053", "start": 32950, "length": 33}, {"loc": "urn:cts:greekLit:tlg0085.tlg004:1054", "start": 32983, "length": 40}, {"loc": "urn:cts:greekLit:tlg0085.tlg004:1055", "start": 33023, "length": 34}, {"loc": "urn:cts:greekLit:tlg0085.tlg004:1056", "start": 33057, "length": 42}, {"loc": "urn:cts:greekLit:tlg0085.tlg004:1057", "start": 33099, "length": 33}, {"loc": "urn:cts:greekLit:tlg0085.tlg004:1058", "start": 33132, "length": 34}, {"loc": "urn:cts:greekLit:tlg0085.tlg004:1059", "start": 33166, "length": 39}, {"loc": "urn:cts:greekLit:tlg0085.tlg004:1059b", "start": 33205, "length": 9}, {"loc": "urn:cts:greekLit:tlg0085.tlg004:1060", "start": 33214, "length": 30}, {"loc": "urn:cts:greekLit:tlg0085.tlg004:1061", "start": 33244, "length": 29}, {"loc": "urn:cts:greekLit:tlg0085.tlg004:1062", "start": 33273, "length": 31}, {"loc": "urn:cts:greekLit:tlg0085.tlg004:1063", "start": 33304, "length": 36}, {"loc": "urn:cts:greekLit:tlg0085.tlg004:1064", "start": 33340, "length": 28}, {"loc": "urn:cts:greekLit:tlg0085.tlg004:1065", "start": 33368, "length": 29}, {"loc": "urn:cts:greekLit:tlg0085.tlg004:1066", "start": 33397, "length": 27}, {"loc": "urn:cts:greekLit:tlg0085.tlg004:1067", "start": 33424, "length": 15}, {"loc": "urn:cts:greekLit:tlg0085.tlg004:1068", "start": 33439, "length": 28}, {"loc": "urn:cts:greekLit:tlg0085.tlg004:1069", "start": 33467, "length": 32}, {"loc": "urn:cts:greekLit:tlg0085.tlg004:1070", "start": 33499, "length": 32}, {"loc": "urn:cts:greekLit:tlg0085.tlg004:1071", "start": 33531, "length": 31}, {"loc": "urn:cts:greekLit:tlg0085.tlg004:1072", "start": 33562, "length": 28}, {"loc": "urn:cts:greekLit:tlg0085.tlg004:1073", "start": 33590, "length": 26}, {"loc": "urn:cts:greekLit:tlg0085.tlg004:1074", "start": 33616, "length": 30}, {"loc": "urn:cts:greekLit:tlg0085.tlg004:1075", "start": 33646, "length": 30}, {"loc": "urn:cts:greekLit:tlg0085.tlg004:1076", "start": 33676, "length": 34}, {"loc": "urn:cts:greekLit:tlg0085.tlg004:1077", "start": 33710, "length": 26}, {"loc": "urn:cts:greekLit:tlg0085.tlg004:1078", "start": 33736, "length": 34}, {"loc": "urn:cts:greekLit:tlg0085.tlg004:1079", "start": 33770, "length": 27}, {"loc": "urn:cts:greekLit:tlg0085.tlg004:1080", "start": 33797, "length": 32}, {"loc": "urn:cts:greekLit:tlg0085.tlg004:1081", "start": 33829, "length": 25}, {"loc": "urn:cts:greekLit:tlg0085.tlg004:1082", "start": 33854, "length": 29}, {"loc": "urn:cts:greekLit:tlg0085.tlg004:1083", "start": 33883, "length": 13}, {"loc": "urn:cts:greekLit:tlg0085.tlg004:1084", "start": 33896, "length": 26}]