[{"loc": "urn:cts:greekLit:tlg0014.tlg001:1", "start": 0, "length": 473}, {"loc": "urn:cts:greekLit:tlg0014.tlg001:2", "start": 473, "length": 457}, {"loc": "urn:cts:greekLit:tlg0014.tlg001:3", "start": 930, "length": 263}, {"loc": "urn:cts:greekLit:tlg0014.tlg001:4", "start": 1193, "length": 427}, {"loc": "urn:cts:greekLit:tlg0014.tlg001:5", "start": 1620, "length": 321}, {"loc": "urn:cts:greekLit:tlg0014.tlg001:6", "start": 1941, "length": 319}, {"loc": "urn:cts:greekLit:tlg0014.tlg001:7", "start": 2260, "length": 365}, {"loc": "urn:cts:greekLit:tlg0014.tlg001:8", "start": 2625, "length": 452}, {"loc": "urn:cts:greekLit:tlg0014.tlg001:9", "start": 3077, "length": 564}, {"loc": "urn:cts:greekLit:tlg0014.tlg001:10", "start": 3641, "length": 434}, {"loc": "urn:cts:greekLit:tlg0014.tlg001:11", "start": 4075, "length": 527}, {"loc": "urn:cts:greekLit:tlg0014.tlg001:12", "start": 4602, "length": 393}, {"loc": "urn:cts:greekLit:tlg0014.tlg001:13", "start": 4995, "length": 337}, {"loc": "urn:cts:greekLit:tlg0014.tlg001:14", "start": 5332, "length": 456}, {"loc": "urn:cts:greekLit:tlg0014.tlg001:15", "start": 5788, "length": 494}, {"loc": "urn:cts:greekLit:tlg0014.tlg001:16", "start": 6282, "length": 411}, {"loc": "urn:cts:greekLit:tlg0014.tlg001:17", "start": 6693, "length": 213}, {"loc": "urn:cts:greekLit:tlg0014.tlg001:18", "start": 6906, "length": 398}, {"loc": "urn:cts:greekLit:tlg0014.tlg001:19", "start": 7304, "length": 405}, {"loc": "urn:cts:greekLit:tlg0014.tlg001:20", "start": 7709, "length": 491}, {"loc": "urn:cts:greekLit:tlg0014.tlg001:21", "start": 8200, "length": 452}, {"loc": "urn:cts:greekLit:tlg0014.tlg001:22", "start": 8652, "length": 454}, {"loc": "urn:cts:greekLit:tlg0014.tlg001:23", "start": 9106, "length": 393}, {"loc": "urn:cts:greekLit:tlg0014.tlg001:24", "start": 9499, "length": 456}, {"loc": "urn:cts:greekLit:tlg0014.tlg001:25", "start": 9955, "length": 354}, {"loc": "urn:cts:greekLit:tlg0014.tlg001:26", "start": 10309, "length": 271}, {"loc": "urn:cts:greekLit:tlg0014.tlg001:27", "start": 10580, "length": 507}, {"loc": "urn:cts:greekLit:tlg0014.tlg001:28", "start": 11087, "length": 515}]