[{"loc": "urn:cts:greekLit:tlg0007.tlg125:1", "start": 0, "length": 1357}, {"loc": "urn:cts:greekLit:tlg0007.tlg125:2", "start": 1357, "length": 2019}, {"loc": "urn:cts:greekLit:tlg0007.tlg125:3", "start": 3376, "length": 1043}, {"loc": "urn:cts:greekLit:tlg0007.tlg125:4", "start": 4419, "length": 722}, {"loc": "urn:cts:greekLit:tlg0007.tlg125:5", "start": 5141, "length": 1745}, {"loc": "urn:cts:greekLit:tlg0007.tlg125:6", "start": 6886, "length": 686}, {"loc": "urn:cts:greekLit:tlg0007.tlg125:7", "start": 7572, "length": 851}, {"loc": "urn:cts:greekLit:tlg0007.tlg125:8", "start": 8423, "length": 397}, {"loc": "urn:cts:greekLit:tlg0007.tlg125:9", "start": 8820, "length": 747}, {"loc": "urn:cts:greekLit:tlg0007.tlg125:10", "start": 9567, "length": 717}, {"loc": "urn:cts:greekLit:tlg0007.tlg125:11", "start": 10284, "length": 611}, {"loc": "urn:cts:greekLit:tlg0007.tlg125:12", "start": 10895, "length": 812}, {"loc": "urn:cts:greekLit:tlg0007.tlg125:13", "start": 11707, "length": 913}, {"loc": "urn:cts:greekLit:tlg0007.tlg125:14", "start": 12620, "length": 436}, {"loc": "urn:cts:greekLit:tlg0007.tlg125:15", "start": 13056, "length": 402}, {"loc": "urn:cts:greekLit:tlg0007.tlg125:16", "start": 13458, "length": 542}, {"loc": "urn:cts:greekLit:tlg0007.tlg125:17", "start": 14000, "length": 256}, {"loc": "urn:cts:greekLit:tlg0007.tlg125:18", "start": 14256, "length": 561}, {"loc": "urn:cts:greekLit:tlg0007.tlg125:19", "start": 14817, "length": 2247}, {"loc": "urn:cts:greekLit:tlg0007.tlg125:20", "start": 17064, "length": 697}, {"loc": "urn:cts:greekLit:tlg0007.tlg125:21", "start": 17761, "length": 1234}, {"loc": "urn:cts:greekLit:tlg0007.tlg125:22", "start": 18995, "length": 366}, {"loc": "urn:cts:greekLit:tlg0007.tlg125:23", "start": 19361, "length": 757}, {"loc": "urn:cts:greekLit:tlg0007.tlg125:24", "start": 20118, "length": 420}, {"loc": "urn:cts:greekLit:tlg0007.tlg125:25", "start": 20538, "length": 620}, {"loc": "urn:cts:greekLit:tlg0007.tlg125:26", "start": 21158, "length": 1522}, {"loc": "urn:cts:greekLit:tlg0007.tlg125:27", "start": 22680, "length": 550}, {"loc": "urn:cts:greekLit:tlg0007.tlg125:28", "start": 23230, "length": 546}, {"loc": "urn:cts:greekLit:tlg0007.tlg125:29", "start": 23776, "length": 665}, {"loc": "urn:cts:greekLit:tlg0007.tlg125:30", "start": 24441, "length": 400}, {"loc": "urn:cts:greekLit:tlg0007.tlg125:31", "start": 24841, "length": 729}, {"loc": "urn:cts:greekLit:tlg0007.tlg125:32", "start": 25570, "length": 508}, {"loc": "urn:cts:greekLit:tlg0007.tlg125:33", "start": 26078, "length": 540}, {"loc": "urn:cts:greekLit:tlg0007.tlg125:34", "start": 26618, "length": 457}, {"loc": "urn:cts:greekLit:tlg0007.tlg125:35", "start": 27075, "length": 462}, {"loc": "urn:cts:greekLit:tlg0007.tlg125:36", "start": 27537, "length": 678}, {"loc": "urn:cts:greekLit:tlg0007.tlg125:37", "start": 28215, "length": 619}, {"loc": "urn:cts:greekLit:tlg0007.tlg125:38", "start": 28834, "length": 627}, {"loc": "urn:cts:greekLit:tlg0007.tlg125:39", "start": 29461, "length": 765}]