[{"loc": "urn:cts:greekLit:tlg0059.tlg028:234", "start": 0, "length": 731}, {"loc": "urn:cts:greekLit:tlg0059.tlg028:235", "start": 731, "length": 2368}, {"loc": "urn:cts:greekLit:tlg0059.tlg028:236", "start": 3099, "length": 2119}, {"loc": "urn:cts:greekLit:tlg0059.tlg028:237", "start": 5218, "length": 1854}, {"loc": "urn:cts:greekLit:tlg0059.tlg028:238", "start": 7072, "length": 1864}, {"loc": "urn:cts:greekLit:tlg0059.tlg028:239", "start": 8936, "length": 1933}, {"loc": "urn:cts:greekLit:tlg0059.tlg028:240", "start": 10869, "length": 2085}, {"loc": "urn:cts:greekLit:tlg0059.tlg028:241", "start": 12954, "length": 1891}, {"loc": "urn:cts:greekLit:tlg0059.tlg028:242", "start": 14845, "length": 1793}, {"loc": "urn:cts:greekLit:tlg0059.tlg028:243", "start": 16638, "length": 1933}, {"loc": "urn:cts:greekLit:tlg0059.tlg028:244", "start": 18571, "length": 1944}, {"loc": "urn:cts:greekLit:tlg0059.tlg028:245", "start": 20515, "length": 1944}, {"loc": "urn:cts:greekLit:tlg0059.tlg028:246", "start": 22459, "length": 2066}, {"loc": "urn:cts:greekLit:tlg0059.tlg028:247", "start": 24525, "length": 1949}, {"loc": "urn:cts:greekLit:tlg0059.tlg028:248", "start": 26474, "length": 1897}, {"loc": "urn:cts:greekLit:tlg0059.tlg028:249", "start": 28371, "length": 2121}]